Workbook

Sheet Tablero
A1: TABLERO DE CRECIMIENTO — Marco YC (ERP + Agentes 2 semanas)
A2: Métricas que importan: WAU Agentes · NRR/Churn ERP · CAC vs LTV · Crecimiento WoW. Amarillo = supuestos que TÚ ajustas.
A4: SUPUESTOS DE MOTOR OUTBOUND
A5: Reps outbound (FTE humanos) | B5: 2
A6: Toques netos / día por rep (asistido por agentes) | B6: 40 | C6: 1er contacto efectivo
A7: Días hábiles / semana | B7: 5
A8: Reparto de capacidad a TMS (resto va a IPS) | B8: 0.5 | C8: %
A9: Tasa: toque → conexión con decisor | B9: 0.25 | C9: %
A10: Tasa: conexión → reunión / demo | B10: 0.2 | C10: %
A11: Tasa: reunión → piloto agente (deploy 2 sem) | B11: 0.35 | C11: %
A12: Tasa: piloto → cuenta ERP (land & expand) | B12: 0.15 | C12: %
A13: Meta de crecimiento semanal (WoW) | B13: 0.06 | C13: 5-7% objetivo PMF
A15: EMBUDO SEMANAL (capacidad total → resultados)
A16: Toques / día (todo el equipo) | B16: =B5*B6 -> 80
A17: Toques / semana | B17: =B16*B7 -> 400
A18: Conexiones con decisor / semana | B18: =B17*B9 -> 100
A19: Reuniones / demos / semana | B19: =B18*B10 -> 20
A20: Pilotos de agente / semana | B20: =B19*B11 -> 7
A21: Cuentas ERP nuevas / semana (steady-state) | B21: =B20*B12 -> 1.05
A23: COBERTURA DEL UNIVERSO
A24: Empresas TMS activas | B24: ='Universo TMS'!C25 -> 4175
A25: IPS privadas Bogotá (únicas) | B25: =IPS!B2 -> 3386
A26: Universo combinado (TMS+IPS) | B26: =B24+B25 -> 7561
A27: Semanas para 1 pasada combinada (capacidad total) | B27: =B26/B17 -> 18.9025
A28: Semanas para duplicar (a meta WoW) | B28: =LN(2)/LN(1+B13) -> 11.895661
A30: MÉTRICAS YC — DEFINICIÓN Y META
A31: Métrica | B31: Definición / fórmula | C31: Meta | D31: Por qué importa
A32: WAU Agentes | B32: Empresas que usan el agente ≥1 vez/semana | C32: crecer 6%+ WoW | D32: Valor real, no vanity
A33: NRR (ERP) | B33: (MRR inicio + expansión − contracción − churn)/MRR inicio | C33: ≥ 110% | D33: Land & expand sano
A34: Churn lógico ERP | B34: Cuentas ERP perdidas / total (mes) | C34: < 2% mensual | D34: ERP debe pegar
A35: CAC | B35: (Ventas+Mkt) / cuentas nuevas | C35: ↓ con agentes | D35: Eficiencia de capital
A36: LTV | B36: Ticket × margen bruto / churn | C36: — | D36: Techo de unit economics
A37: LTV / CAC | B37: LTV ÷ CAC | C37: ≥ 3.0x | D37: Umbral de aceleradora top
A38: Crecimiento WoW | B38: (Sem actual − previa)/previa | C38: 5–7% | D38: Velocidad a PMF
A40: UNIT ECONOMICS (ajusta amarillos)
A41: Ticket ERP mensual (COP) | B41: 2500000
A42: Margen bruto | B42: 0.75
A43: Churn mensual ERP | B43: 0.02
A44: CAC por cuenta (COP) | B44: 6000000
A45: LTV (COP) | B45: =B41*B42/B43 -> 93750000
A46: LTV / CAC | B46: =B45/B44 -> 15.625

Sheet Universo TMS
A1: UNIVERSO TMS — Empresas de transporte de carga habilitadas (ACTIVAS) por departamento
A2: Conteo derivado del listado de habilitación. Ordenado por tamaño; tier por concentración (80/20).
A4: # | B4: Departamento | C4: Empresas | D4: % del universo | E4: % acumulado | F4: Tier de ataque
A5: 1 | B5: Cundinamarca / Bogotá | C5: 1255 | D5: =C5/$C$25 -> 0.3005988 | E5: =D5 -> 0.3005988 | F5: Tier 1
A6: 2 | B6: Antioquia | C6: 514 | D6: =C6/$C$25 -> 0.12311377 | E6: =E5+D6 -> 0.42371257 | F6: Tier 1
A7: 3 | B7: Atlántico | C7: 315 | D7: =C7/$C$25 -> 0.075449102 | E7: =E6+D7 -> 0.49916168 | F7: Tier 1
A8: 4 | B8: Bolívar | C8: 307 | D8: =C8/$C$25 -> 0.073532934 | E8: =E7+D8 -> 0.57269461 | F8: Tier 2
A9: 5 | B9: Boyacá | C9: 307 | D9: =C9/$C$25 -> 0.073532934 | E9: =E8+D9 -> 0.64622754 | F9: Tier 2
A10: 6 | B10: Meta | C10: 274 | D10: =C10/$C$25 -> 0.065628743 | E10: =E9+D10 -> 0.71185629 | F10: Tier 2
A11: 7 | B11: Valle del Cauca | C11: 261 | D11: =C11/$C$25 -> 0.06251497 | E11: =E10+D11 -> 0.77437126 | F11: Tier 2
A12: 8 | B12: Santander | C12: 211 | D12: =C12/$C$25 -> 0.050538922 | E12: =E11+D12 -> 0.82491018 | F12: Tier 2
A13: 9 | B13: Norte de Santander | C13: 123 | D13: =C13/$C$25 -> 0.029461078 | E13: =E12+D13 -> 0.85437126 | F13: Tier 3
A14: 10 | B14: Cesar | C14: 113 | D14: =C14/$C$25 -> 0.027065868 | E14: =E13+D14 -> 0.88143713 | F14: Tier 3
A15: 11 | B15: Magdalena | C15: 111 | D15: =C15/$C$25 -> 0.026586826 | E15: =E14+D15 -> 0.90802395 | F15: Tier 3
A16: 12 | B16: Huila | C16: 108 | D16: =C16/$C$25 -> 0.025868263 | E16: =E15+D16 -> 0.93389222 | F16: Tier 3
A17: 13 | B17: Nariño | C17: 105 | D17: =C17/$C$25 -> 0.025149701 | E17: =E16+D17 -> 0.95904192 | F17: Tier 3
... A24: 20 | B24: Cauca | C24: 10 | D24: =C24/$C$25 -> 0.0023952096 | E24: =E23+D24 -> 1 | F24: Tier 3
B25: TOTAL TMS | C25: =SUM(C5:C24) -> 4175 | D25: =SUM(D5:D24) -> 1

Sheet Plan de Contacto
A1: PLAN DE CONTACTO — Metas diarias y semanales por vertical
A3: METAS GLOBALES POR VERTICAL (capacidad repartida según Tablero)
A4: Vertical | B4: Universo | C4: Meta toques/día | D4: Meta toques/semana | E4: Semanas 1 pasada | F4: Pilotos/sem (meta)
A5: TMS (transporte de carga) | B5: ='Universo TMS'!C25 -> 4175 | C5: =Tablero!B16*Tablero!B8 -> 40 | D5: =Tablero!B17*Tablero!B8 -> 200 | E5: =B5/D5 -> 20.875 | F5: =Tablero!B20*Tablero!B8 -> 3.5
A6: IPS privadas Bogotá | B6: =IPS!B2 -> 3386 | C6: =Tablero!B16*(1-Tablero!B8) -> 40 | D6: =Tablero!B17*(1-Tablero!B8) -> 200 | E6: =B6/D6 -> 16.93 | F6: =Tablero!B20*(1-Tablero!B8) -> 3.5
A7: COMBINADO (capacidad total) | B7: =B5+B6 -> 7561 | C7: =Tablero!B16 -> 80 | D7: =Tablero!B17 -> 400 | E7: =B7/D7 -> 18.9025 | F7: =Tablero!B20 -> 7
A8: Con reparto 50/50: TMS y IPS corren en paralelo. Cambia el % en Tablero para priorizar una vertical.
A10: IPS BOGOTÁ — ORDEN DE ATAQUE POR READINESS
A11: Prioridad | B11: Segmento | C11: IPS | D11: Semanas (a meta IPS)
A12: 1 | B12: A · Lista (gerente+email) → contactar YA | C12: =IPS!B3 -> 2820 | D12: =C12/D6 -> 14.1
A13: 2 | B13: B · Con canal (sin gerente) → enriquecer gerente | C13: =IPS!B4 -> 548 | D13: =C13/D6 -> 2.74
A14: 3 | B14: C · Requiere enriquecimiento (sin email/tel) | C14: =IPS!B5 -> 18 | D14: =C14/D6 -> 0.09
A16: SECUENCIA DE ATAQUE TMS (cronograma por región, a la capacidad asignada a TMS)
A17: Orden | B17: Región | C17: Empresas | D17: Días para cubrir | E17: Semana inicio | F17: Semana fin (acum.)
A18: 1 | B18: Cundinamarca / Bogotá | C18: ='Universo TMS'!C5 -> 1255 | D18: =C18/($C$5) -> 31.375 | E18: 0 | F18: =C18/$D$5 -> 6.275
A19: 2 | B19: Antioquia | C19: ='Universo TMS'!C6 -> 514 | D19: =C19/($C$5) -> 12.85 | E19: =F18 -> 6.275 | F19: =F18+C19/$D$5 -> 8.845
A20: 3 | B20: Atlántico | C20: ='Universo TMS'!C7 -> 315 | D20: =C20/($C$5) -> 7.875 | E20: =F19 -> 8.845 | F20: =F19+C20/$D$5 -> 10.42
A21: 4 | B21: Bolívar | C21: ='Universo TMS'!C8 -> 307 | D21: =C21/($C$5) -> 7.675 | E21: =F20 -> 10.42 | F21: =F20+C21/$D$5 -> 11.955
A22: 5 | B22: Boyacá | C22: ='Universo TMS'!C9 -> 307 | D22: =C22/($C$5) -> 7.675 | E22: =F21 -> 11.955 | F22: =F21+C22/$D$5 -> 13.49
A23: 6 | B23: Meta | C23: ='Universo TMS'!C10 -> 274 | D23: =C23/($C$5) -> 6.85 | E23: =F22 -> 13.49 | F23: =F22+C23/$D$5 -> 14.86
A24: 7 | B24: Valle del Cauca | C24: ='Universo TMS'!C11 -> 261 | D24: =C24/($C$5) -> 6.525 | E24: =F23 -> 14.86 | F24: =F23+C24/$D$5 -> 16.165
A25: 8 | B25: Santander | C25: ='Universo TMS'!C12 -> 211 | D25: =C25/($C$5) -> 5.275 | E25: =F24 -> 16.165 | F25: =F24+C25/$D$5 -> 17.22
A26: 9 | B26: Norte de Santander | C26: ='Universo TMS'!C13 -> 123 | D26: =C26/($C$5) -> 3.075 | E26: =F25 -> 17.22 | F26: =F25+C26/$D$5 -> 17.835
A27: 10 | B27: Cesar | C27: ='Universo TMS'!C14 -> 113 | D27: =C27/($C$5) -> 2.825 | E27: =F26 -> 17.835 | F27: =F26+C27/$D$5 -> 18.4
A28: 11 | B28: Magdalena | C28: ='Universo TMS'!C15 -> 111 | D28: =C28/($C$5) -> 2.775 | E28: =F27 -> 18.4 | F28: =F27+C28/$D$5 -> 18.955
A29: 12 | B29: Huila | C29: ='Universo TMS'!C16 -> 108 | D29: =C29/($C$5) -> 2.7 | E29: =F28 -> 18.955 | F29: =F28+C29/$D$5 -> 19.495
A30: 13 | B30: Nariño | C30: ='Universo TMS'!C17 -> 105 | D30: =C30/($C$5) -> 2.625 | E30: =F29 -> 19.495 | F30: =F29+C30/$D$5 -> 20.02
... A37: 20 | B37: Cauca | C37: ='Universo TMS'!C24 -> 10 | D37: =C37/($C$5) -> 0.25 | E37: =F36 -> 20.825 | F37: =F36+C37/$D$5 -> 20.875
B38: TOTAL | C38: =SUM(C18:C37) -> 4175 | F38: =F37 -> 20.875

Sheet CRM TMS
A1: CRM TMS — Pipeline (pega aquí el listado completo; incluye semilla enriquecida de Cundinamarca)
A3: NIT | B3: Empresa | C3: Departamento | D3: Sitio web | E3: Contacto (nombre/cargo) | F3: Email / WhatsApp | G3: LinkedIn gerente | H3: Tier | I3: Canal 1er toque | J3: Estado | K3: Fecha contacto | L3: Responsable | M3: Notas
A4: 800037047 | B4: TRANSPORTES AUTO ALFAN LTDA | C4: Cundinamarca | D4: trans-autoalfan.com | E4: Luis Alberto Zamora - Gte Operacional | F4: (601) 4118128 | H4: Tier 1 | I4: Llamada/WhatsApp | J4: Por contactar
A5: 900050309 | B5: CARGA MUDANZAS COLOMBIA S.A. | C5: Cundinamarca | D5: cargamudanzas.com | E5: Gerencia General | F5: (601) 8937660 | H5: Tier 1 | I5: Llamada | J5: Por contactar
A6: 830096376 | B6: TRANSPORTES HUMADEA LTDA. | C6: Cundinamarca | D6: humadea.com.co | E6: Gerencia / Coord. Comercial | F6: contacto@humadea.com.co | H6: Tier 1 | I6: Email | J6: Por contactar
A7: 860048617 | B7: COOP. TRANSPORTADORES DE ZIPAQUIRA | C7: Cundinamarca | D7: cootranszipa.com.co | E7: Wilmar Gomez - Pte. Consejo | F7: gerencia@cootranszipa.com.co | H7: Tier 1 | I7: Email | J7: Por contactar
A8: 860052980 | B8: SURAMERICANA DE TRANSPORTES S.A. | C8: Cundinamarca | D8: suramericanadetransportes.com | E8: Dirección Comercial | F8: Comercial@suratrans.com | H8: Tier 1 | I8: Email | J8: Por contactar
A9: 800049934 | B9: CIA. COLOMBIANA DE CARGA CONCARGA S.A. | C9: Cundinamarca | D9: concarga.co | E9: Gerencia Comercial | F9: 3164018106 | H9: Tier 1 | I9: WhatsApp | J9: Por contactar
A10: 830042504 | B10: TRANSPORTES DE CARGA NACIONAL LTDA | C10: Cundinamarca | D10: tcnltda.com | E10: Gerencia Ventas | F10: ventas@tcnltda.com | H10: Tier 1 | I10: Email | J10: Por contactar
A11: 800121921 | B11: ENERPETROL S.A. | C11: Cundinamarca | D11: enerpetrolsa.com | E11: Gerencia General | F11: gerencia@enerpetrolsa.com | H11: Tier 1 | I11: Email | J11: Por contactar
A12: 860026744 | B12: AGIL CARGO S.A.S (ALDIA) | C12: Cundinamarca | D12: aldialogistica.com | E12: Leonel Molina Varela | F12: lemolvar@gmail.com / 3164823240 | H12: Tier 1 | I12: WhatsApp | J12: Por contactar
A13: 890903501 | B13: INTERANDINA DE TRANSPORTES S.A. | C13: Cundinamarca | D13: inantra.com | E13: Gerencia General | F13: (601) 8299703 | H13: Tier 1 | I13: Llamada | J13: Por contactar
A14: 800081833 | B14: LINEAS TECNICAS DE CARGAMENTO S.A. | C14: Cundinamarca | D14: litecar.com | E14: Gerencia General | F14: (601) 8964170 | H14: Tier 1 | I14: Llamada | J14: Por contactar
A15: 860450987 | B15: TRANSPORTES JOALCO S.A. | C15: Cundinamarca | D15: transjoalco.com.co | E15: Gerencia / Servicio Cliente | F15: servicioalcliente@transjoalco.com.co | H15: Tier 1 | I15: Email | J15: Por contactar
... A21: 800185306 | B21: COLVANES S.A.S. (ENVIA) | C21: Cundinamarca | D21: envia.co | E21: Henry A. Cubides Moreno - Rep. Legal | F21: contactanos@envia.co | H21: Tier 1 | I21: Email | J21: Por contactar

Sheet IPS
A1: IPS PRIVADAS BOGOTÁ — Universo de contacto (gerente · email · teléfono ya enriquecidos)
A2: Total IPS únicas: | B2: =COUNTA($B$8:$B$100000) -> 3386
A3: A · Lista (gerente+email): | B3: =COUNTIF($H$8:$H$100000,"A*") -> 2820
A4: B · Con canal (sin gerente): | B4: =COUNTIF($H$8:$H$100000,"B*") -> 548
A5: C · Requiere enriquecimiento: | B5: =COUNTIF($H$8:$H$100000,"C*") -> 18
A6: Ordenadas por readiness (A primero). Empieza por las A.
A7: Código | B7: IPS | C7: Gerente | D7: Dirección | E7: Teléfono | F7: Email | G7: URL | H7: Readiness | I7: Canal 1er toque | J7: Estado | K7: Fecha | L7: Responsable | M7: Notas
A8: 110011953201 | B8: & ACOMPAÑAMIENTO INTEGRAL AMBULATORIO Y DOMICILIARIO | C8: HENRY ALARCON LOPEZ | D8: CALLE 119A NO 70-15 | E8: 7026848 | F8: henry.alarcon@saiadltda.com | H8: A · Lista (gerente+email) | I8: Email | J8: Por contactar
A9: 110014019201 | B9: 11:11 LOOKING GOOD TECHNOLOGIES S.A.S SIGLA 11:11 LGT | C9: Paula Andrea Puentes Guevara | D9: Carrera 19 # 84 - 17 Of 601 Consultorio 1 | E9: 3043800648 | F9: contacto@doctoreternal.com | H9: A · Lista (gerente+email) | I9: Email | J9: Por contactar
A10: 110012817401 | B10: 14-85 DENTAL SPA S.A.S | C10: BEATRIZ EUGENIA TORO PEÑA | D10: CARRERA 14 No. 85-68 OF 303 | E10: 3157056255 | F10: gerencia2@1485dentalspa.com | H10: A · Lista (gerente+email) | I10: Email | J10: Por contactar
A11: 110012817403 | B11: 14-85 DENTAL SPA SALITRE | C11: JEAN-FRANCOIS HENO | D11: Carrera 68B # 24 - 39 LOCAL 3-19 - 3-21 | E11: 3157056255 | F11: gerencia2@1485dentalspa.com | H11: A · Lista (gerente+email) | I11: Email | J11: Por contactar
A12: 110012817402 | B12: 14-85 DENTAL SPA UNICENTRO | C12: JEAN FRANCOIS MARIE HENO | D12: CL 119 #14-42 LC2 PISOS 1 y 2 | E12: 3157056255 | F12: gerencia2@1485dentalspa.com | H12: A · Lista (gerente+email) | I12: Email | J12: Por contactar
A13: 110013961501 | B13: 3D Centro Imagenes Diagnosticas | C13: LIZETH JULIANA ARENAS CARDENAS | D13: AK 9# 127B-16 LOCAL 3 | E13: 3001959807 | F13: gerencia@3dcentrodid.com | H13: A · Lista (gerente+email) | I13: Email | J13: Por contactar
A14: 110010985901 | B14: A UNO DENTAL COLOR | C14: LUIS FERNANDO ORTIZ RODRIGUEZ | D14: AC 53 # 59 03 | E14: 2220297 | F14: aunodentalcolor@hotmail.com | H14: A · Lista (gerente+email) | I14: Email | J14: Por contactar
A15: 110014000101 | B15: A&E SALUD ODONTOLOGIA | C15: ORLANDO HERRERA MESINO | D15: Calle 125 #21A-18 Piso 2 Oficina 205 Edif Foma 97 | E15: 3123529707 | F15: AESALUD@AESALUD.COM.CO | H15: A · Lista (gerente+email) | I15: Email | J15: Por contactar
A16: 110011242501 | B16: A&G SERVICIOS DE SALUD S.A.S | C16: SONIA PATRICIA CASTRO ZARATE | D16: AC 127 # 71 96 | E16: 7455901-7455902-7455905 | F16: gerencia@aygserviciosdesalud.com | H16: A · Lista (gerente+email) | I16: Email | J16: Por contactar
A17: 1100112425 | B17: A&G SERVICIOS DE SALUD S.A.S. | C17: RICHARD GOMEZ SILVA | D17: AC 127 # 71 96 | E17: 7455901-7455902-7455905 | F17: auditorensalud@aygserviciosdesalud.com | H17: A · Lista (gerente+email) | I17: Email | J17: Por contactar
A18: 1100109757 | B18: AAAA ACADEMIA ABSCRITA A ASOCIACION DE ESPECIALISTAS S.A.S | C18: VIVAS TROCHEZ ALVARO LEON | D18: AV CARACAS # 30 51 | E18: 3124354990 | F18: calidad@mascercadeusted.com-Clinicadeespecialistas2005@yahoo.es | H18: A · Lista (gerente+email) | I18: Email | J18: Por contactar
A19: 110014146301 | B19: AB ODONTOLOGIA INTEGRAL | C19: JOSE OMAIRO BUSTOS SANCHEZ | D19: DIAGONAL 23#69-11 LOCAL 2-242 | E19: 31055446905 | F19: abodontologia2242@gmail.com | H19: A · Lista (gerente+email) | I19: Email | J19: Por contactar
... A24: 1100109599 | B24: ADMINISTRADORA COUNTRY S.A.S | C24: BAPTISTE LIEVANO FELIPE | D24: KR 16 # 82 57 | E24: 6013905099 | F24: notificacionescdc@clinicadelcountry.com | H24: A · Lista (gerente+email) | I24: Email | J24: Por contactar
A25: 1100108064 | B25: ADN ANALISIS LTDA | C25: SALAZAR VALLEJO MARCELA | D25: CRA 16 # 82 95 CONS 805 | E25: 2364102 | F25: info@adnanalisislabs.com | G25: www.adnanalisislabs.com | H25: A · Lista (gerente+email) | I25: Email | J25: Por contactar
A26: 1100119508 | B26: ADRIANA CEBALLOS PORRAS E.U. | C26: ADRIANA CEBALLOS PORRAS | D26: DG 53 C N 23 - 44 LC 2 | E26: 3460502 | F26: elitedentalgalerias2008@hotmail.com | H26: A · Lista (gerente+email) | I26: Email | J26: Por contactar
A27: 110013994901 | B27: ADVANCEDERMA CLÍNICA DERMATOLÓGICA AVANZADA IPS S.A.S. Sigla: ADVANCEDERMA. | C27: LUIS FERNANDO GONZALEZ CORTES | D27: CRA 16 No. 88 - 81 OFI 707 - 708 - 709 | E27: 3043821546 | F27: LUISFER1000@GMAIL.COM | H27: A · Lista (gerente+email) | I27: Email | J27: Por contactar
A28: 110012806401 | B28: AEPSI SAS | C28: Yaquelin Huertas Paez | D28: Calle 93 B N° 16 - 08 consultorio 301 | E28: 3016260266 | F28: info@aepsi.com.co | H28: A · Lista (gerente+email) | I28: Email | J28: Por contactar
A29: 110013588302 | B29: AEQUI MOVISTAR | C29: Juliana Montenegro Castillo | D29: CALLE 63A 35 16 | E29: 3144394818 | F29: gerencia@aequi.com.co | H29: A · Lista (gerente+email) | I29: Email | J29: Por contactar
A30: 110013999501 | B30: AEQUSST MEDICINA PREVENTIVA SAS | C30: ADRIANA PRIETO CASTIBLANCO | D30: CALLE 18#9-20 LOCAL 405 | E30: 3102830124 | F30: notificaciones.aequsst@gmail.com | H30: A · Lista (gerente+email) | I30: Email | J30: Por contactar
A31: 110013863401 | B31: AEROMAS SAS | C31: MILLER AUGUSTO VARGAS ZAMORA | D31: Avenida Calle 26 113 81 Aeropuerto Internacional El Dorado En 6 Hg 15 Piso 1 Nzag | E31: 3175867106 | F31: habilitacion@aeromas.com.co | H31: A · Lista (gerente+email) | I31: Email | J31: Por contactar
A32: 110011627501 | B32: AESTHETIC MEDICAL SPA | C32: UMAR JOSE ABELLO RODRIGEZ | D32: KR 10 No. 96 - 25 CS 403 | E32: 6160557 | F32: aestheticmedical1@gmail.com | H32: A · Lista (gerente+email) | I32: Email | J32: Por contactar
A33: 110012139901 | B33: AG INSTITUTE CIRUGÍA PLÁSTICA, RECONSTRUCTIVA Y SALUD ESTETICA I.P.S. S.A.S | C33: JAMES ALEXIS ZAMBRANO HERNÁNDEZ | D33: Carrera 7 BIS No 124 - 26 Oficina 201 | E33: 7424270 | F33: contacto@alangonzalez.com | H33: A · Lista (gerente+email) | I33: Email | J33: Por contactar
A34: 110012223501 | B34: AGUA SPA ALEXANDRA GARCIA | C34: NELLY YADIRA DALEL MARTINEZ | D34: CRA 15 No. 134 -21 | E34: 3112500492 | F34: misapita1234@hotmail.com | H34: A · Lista (gerente+email) | I34: Email | J34: Por contactar
A35: 110013890201 | B35: AI-RAD | C35: MARIO ENRIQUE JOYA GALIANO | D35: Cr 19 A No 82-85 Consultorio 304 - 307 | E35: 3174379410 | F35: calidad@rimab.com.co | H35: A · Lista (gerente+email) | I35: Email | J35: Por contactar
A36: 110013561901 | B36: AIR LIQUIDE COLOMBIA AGENCIA LA CASTELLANA | C36: YESMIT JOHANNA ARCINIEGAS LADINO | D36: AK 45 # 94 23 TO A PI 2 | E36: 6017424444 | F36: calidad-salud@airliquide.com | H36: A · Lista (gerente+email) | I36: Email | J36: Por contactar
A37: 110013561902 | B37: AIR LIQUIDE COLOMBIA AGENCIA LAS AMERICAS | C37: PIERRE MARIE VALTON | D37: Carrera 44 No 14-95 P 2 | E37: 6017424444 | F37: calidad-salud@airliquide.com | H37: A · Lista (gerente+email) | I37: Email | J37: Por contactar
... A87: 110010562001 | B87: APRENDAMOS JUNTOS | C87: SEBASTIAN PELAEZ PEREZ | D87: CL 135A # 10 - 39 piso 1 | E87: 3047026 | F87: ajuntos2@gmail.com | H87: A · Lista (gerente+email) | I87: Email | J87: Por contactar
A88: 1100116660 | B88: ARCANGELES FUNDACION PARA LA REHABILITACION INTEGRAL | C88: JUAN PABLO SALAZAR SALAMANCA | D88: Cra 7 B bis# 132-38 Piso 9 y 10 Edificio Forest Medical Center | E88: 3336025204 | F88: direccionejecutiva@arcangeles.org | G88: www.arcangeles.org | H88: A · Lista (gerente+email) | I88: Email | J88: Por contactar
A89: 110014235201 | B89: ARCE 32 ALTA ESTÉTICA DENTAL S.A.S. | C89: LARRY ORTEGA JIMENEZ | D89: KR 12 No. 98 64 OF 507 ED. ALTHEA | E89: 3007315528 | F89: arce32dental@gmail.com | H89: A · Lista (gerente+email) | I89: Email | J89: Por contactar
A90: 110012075501 | B90: ARCHILA Y RICAURTE SAS | C90: MARIA DEL PILAR ARCHILA GOMEZ | D90: AK 7 N 119-14 CS 302 P3 | E90: 2152945 | F90: archilayricaurte@gmail.com | H90: A · Lista (gerente+email) | I90: Email | J90: Por contactar
A91: 110012731701 | B91: ARCOIRIS DE ESPERANZA S.A.S | C91: Lina Paola Bermudez Piñeros | D91: CARRERA 73 NUMERO 55 78 BARRIO NORMANDIA | E91: 3107732715/3143692116/6019158910 | F91: ipsade@arcoirisdeesperanza.com | H91: A · Lista (gerente+email) | I91: Email | J91: Por contactar
A92: 110012175901 | B92: ARIZALUD | C92: LUIS FERNANDO ARIZA HERNANDEZ | D92: TV 87 C # 59 A 23 SUR LC 1 | E92: 9231505-3228493476 | F92: arizalud@gmail.com | H92: A · Lista (gerente+email) | I92: Email | J92: Por contactar
A93: 110014048201 | B93: ARLETH BERNAL PSICOLOGÍA ESPECIALIZADA | C93: Emiro Jose Chica Quiñones | D93: Avenida Carrera 15 # 122 - 35 Consultorio 408 | E93: 3123954053 | F93: arlethpatriciab@gmail.com | H93: A · Lista (gerente+email) | I93: Email | J93: Por contactar
A94: 1100109035 | B94: ARMONIA DENTO FACIAL ADF S.A.S | C94: GONZALEZ MARIÑO MARCOS DANIEL | D94: CARRERA 13 #94A-25/45 OFICINA 501 | E94: 6369188 | F94: madagon.cirumax@gmail.com | H94: A · Lista (gerente+email) | I94: Email | J94: Por contactar
A95: 110012709901 | B95: ARTMEDICA SAS BOGOTA | C95: RICARDO ANTONIO PINEDA TAMAYO | D95: Calle 93 # 19 B 67 Piso 6 Consultorios 605 Y 606 Piso 7 Consultorios 701, 702, 703, 704, 705 Y 706 | E95: Linea de atencion Nacional 3009120074, WhatsApp 3245737308 | F95: notificaciones@artmedica.co | H95: A · Lista (gerente+email) | I95: Email | J95: Por contactar
A96: 110012110401 | B96: ARTRO CENTRO IPS SAS | C96: PAULO ANTONIO ALBAN PULGARIN | D96: CRA 27B # 73-59 PISO 1 | E96: 5405106 3115219789 | F96: pauloalban@artrocentro.com | H96: A · Lista (gerente+email) | I96: Email | J96: Por contactar
A97: 110014319901 | B97: ASIMETRIA CRANEAL COLOMBIA S.A.S. | C97: FERNANDO IGNACIO JIMENO JIMENEZ | D97: Cr 16 No. 84 A 09 Cs 623 624 | E97: 3138997611 | F97: asimetriacranealcolombia@gmail.com | H97: A · Lista (gerente+email) | I97: Email | J97: Por contactar
A98: 110011737701 | B98: ASISFARMA Instituto Medico Bogota | C98: JUAN CARLOS TRUJILLO GARCIA | D98: KR 13 48-26 CONSULTORIO 104 - 201 - 203 - 204 | E98: 2182002 | F98: direccionasistencial@asisfarma.com.co | H98: A · Lista (gerente+email) | I98: Email | J98: Por contactar
A99: 1100117377 | B99: ASISFARMA S.A.S | C99: LUZ MARINA VELANDIA MARTINEZ | D99: KR 13 48-26 CONSULTORIO 104 - 201 - 203 - 204 | E99: 2182002 | F99: direccionasistencial@asisfarma.com.co | H99: A · Lista (gerente+email) | I99: Email | J99: Por contactar
A100: 110011737702 | B100: ASISFARMA SEDE IPS CASTELLANA | C100: JUAN CARLOS TRUJILLO GARCIA | D100: KR 47 # 93 58 | E100: 2182002 | F100: direccionasistencial@asisfarma.com.co | H100: A · Lista (gerente+email) | I100: Email | J100: Por contactar
A101: 110011847702 | B101: ASISTENCIA CIENTIFICA DE ALTA COMPLEJIDAD S.A.S. | C101: B | D101: Carrera 22 # 45C 36 cons 207 | E101: 7444497 - 3004204477 | F101: coord.gerencia@asistenciacientifica.com | H101: A · Lista (gerente+email) | I101: Email | J101: Por contactar
A102: 1100118477 | B102: ASISTENCIA CIENTIFICA DE ALTA COMPLEJIDAD SAS | C102: BERNARDO PACHECO MALDONADO | D102: Calle 45B No. 24 - 25 Primer y Segundo piso | E102: 7444497 - 3004204477 | F102: coord.gerencia@asistenciacientifica.com | G102: 0 | H102: A · Lista (gerente+email) | I102: Email | J102: Por contactar
A103: 110013954701 | B103: ASISTENCIA MEDICA DE BOGOTA IPS SAS - AMEB IPS | C103: SANDRA MILENA GONZALEZ VERGARA | D103: DIAGONAL 45 D # 20-74 CONSULTORIO 105 | E103: 3004932405 | F103: ameb.ips@gmail.com | H103: A · Lista (gerente+email) | I103: Email | J103: Por contactar
A104: 110013678701 | B104: ASISTENCIA MEDICA ESPECIAL EN SALUD IPS SAS SIGLA AMESALUD IPS SAS | C104: YULI MARTINEZ CASTIBLANCO | D104: CALLE 42 SUR 78M 35, PRIMER PISO | E104: 3045779362 | F104: ipsservices2024@gmail.com | H104: A · Lista (gerente+email) | I104: Email | J104: Por contactar
A105: 110012143801 | B105: ASISTENCIA MEDICA INTEGRAL S.A.S. INSTITUCION PRESTADORA DE SERVICIO DE SALUD IPS | C105: EDUARDO GONZALEZ MARIN | D105: Cra 7B Nº 146 - 90 | E105: 6332009 - 6332015 | F105: jefe.calidad@clinicaodontologicaami.com | H105: A · Lista (gerente+email) | I105: Email | J105: Por contactar
A106: 1100111158 | B106: ASISTIR SALUD SAS | C106: JUAN CARLOS CASTILLO MONROY | D106: Calle 64G N° 90A-40 | E106: 601 7441483 - 3187116815 | F106: direcciondecalidad@asistirsalud.com | H106: A · Lista (gerente+email) | I106: Email | J106: Por contactar
A107: 110011115801 | B107: ASISTIR SALUD SAS CANDELARIA | C107: JUAN CARLOS CASTILLO MONROY | D107: Calle 59C Sur No. 51 - 21. Local 120 Centro Comercial Plaza El Ensueño | E107: 601 7441483 - 3187116815 | F107: direcciondecalidad@asistirsalud.com | H107: A · Lista (gerente+email) | I107: Email | J107: Por contactar
A108: 110011115803 | B108: ASISTIR SALUD SAS ENGATIVA | C108: JUAN CARLOS CASTILLO MONROY | D108: CL 64 G # 90 A 40 | E108: 601 7441483 - 3187116815 | F108: direcciondecalidad@asistirsalud.com | H108: A · Lista (gerente+email) | I108: Email | J108: Por contactar
A109: 110011115802 | B109: ASISTIR SALUD SAS FONTIBON | C109: JUAN CARLOS CASTILLO MONROY | D109: KR 99 # 20 C 61 | E109: 601 7441483 - 3187116815 | F109: direcciondecalidad@asistirsalud.com | H109: A · Lista (gerente+email) | I109: Email | J109: Por contactar
A110: 110011115804 | B110: ASISTIR SALUD SAS QUIROGA | C110: JUAN CARLOS CASTILLO MONROY | D110: Avenida Caracas 31-19 Sur | E110: 601 7441483 - 3187116815 | F110: direcciondecalidad@asistirsalud.com | H110: A · Lista (gerente+email) | I110: Email | J110: Por contactar
A111: 110012125501 | B111: ASISTIRTE SAS | C111: RYAN MURILLO SANDOVAL | D111: CRA 22 N 45B-38 CONSULTORIO 508 CENTRO MEDICO PALERMO | E111: 2177186 | F111: jefe.enfermeria@asistirteips.com | H111: A · Lista (gerente+email) | I111: Email | J111: Por contactar
A112: 110013821901 | B112: ASLAB | C112: GERMAN ANTONIO RINCON CASALLAS | D112: CALLE 97 23-37 CONSULTORIO 606, 607 | E112: 53160000 | F112: servicio@acousticsystem.com | H112: A · Lista (gerente+email) | I112: Email | J112: Por contactar
A113: 110012802301 | B113: ASMED SALUD SAS | C113: JUAN JOSE BRAVO AGREDA | D113: CL 4 71 D 73 | E113: 3164541759 - 3173816515 | F113: asmedsaludsas@gmail.com | H113: A · Lista (gerente+email) | I113: Email | J113: Por contactar
A114: 110011625302 | B114: ASMEDAN | C114: HERNANDO TORRES ZULUAGA | D114: AV 1 MAYO # 34- 41 | E114: 3155997385 | F114: rp.valle@grupoasmedan.com | H114: A · Lista (gerente+email) | I114: Email | J114: Por contactar
... A116: 110010099702 | B116: ASOCIACION CENTRO DE ATENCION PARA NIÑOS CON TRASTORNOS SENSORIOMOTORES ""ACONIÑO" | C116: LUISA FERNANDA VARGAS GUTIERREZ | D116: CL 6A No.71A-10 | E116: 2900521 | F116: administracion@aconino.org | H116: A · Lista (gerente+email) | I116: Email | J116: Por contactar
A117: 1100100997 | B117: ASOCIACION CENTRO DE ATENCION PARA NIÑOS CON TRASTORNOS SENSORIOMOTORES ""ACONIÑO""" | C117: ACEVEDO DE RONDEROS BEATRIZ EUGENIA | D117: CALLE 127 B # 45-28 | E117: 6508473 | F117: administracion@aconino.org | G117: http://www.aconino.org/ | H117: A · Lista (gerente+email) | I117: Email | J117: Por contactar
A118: 1100100129 | B118: ASOCIACION CENTRO DE EDUCACION ESPECIAL REHABILITACION Y CAPACITACION RENACER | C118: JOSE ERNESTO CHAPARRO SARMIENTO | D118: CL 33 # 19 36 | E118: 4807256 | F118: insrenacer@hotmail.com | H118: A · Lista (gerente+email) | I118: Email | J118: Por contactar
A119: 1100109295 | B119: ASOCIACION COLOMBIANA DE DIABETES | C119: AMADOR ANDRADE MAURICIO HERNANDO | D119: DG 39 A BIS # 14 78 | E119: 7440888 | F119: adiabete@asodiabetes.org | H119: A · Lista (gerente+email) | I119: Email | J119: Por contactar
A120: 1100107927 | B120: ASOCIACION COLOMBIANA PRO NIÑO CON PARALISIS CEREBRAL -PROPACE | C120: CARDENAS PARRA HUMBERTO | D120: Cra. 54 Nº 65 - 85 CONS 8 SEGUNDO PISO | E120: 2504035 | F120: direccion@propace.org | H120: A · Lista (gerente+email) | I120: Email | J120: Por contactar
A121: 1100103155 | B121: ASOCIACION DE AMIGOS CONTRA EL CANCER PROSEGUIR | C121: GARCIA PARRA GINNA ROCIO | D121: CARRERA 16 No 59-04 Barrio:CHAPINERO | E121: 5557080 EXT 1026 | F121: calidad@proseguir.org | G121: www.proseguir.org | H121: A · Lista (gerente+email) | I121: Email | J121: Por contactar
A122: 110013527501 | B122: ASOCIACION MEDICA PARA LA ATENCION INTEGRAL S.A.S CLINICA NUEVO MONTERREY | C122: JUAN CARLOS TRUJILLO BERNAL | D122: CALLE 102 # 70 B 57 | E122: 3225369493-3203734392 | F122: calidad@nuevomonterrey.com.co | H122: A · Lista (gerente+email) | I122: Email | J122: Por contactar
A123: 1100117312 | B123: ASOCIACION PROMOTORA DE PROYECTOS SERVICIOS ASESORIAS CULTURALES SOCIALES Y ADMINISTRATIVAS - PROACTIVA | C123: JOHAN ADRIAN RUIZ | D123: KR 52 # 70 18 | E123: 5447198 | F123: ASOCIACINPROACTIVA@YAHOO.CES | H123: A · Lista (gerente+email) | I123: Email | J123: Por contactar
A124: 1100110232 | B124: ASOCIACION SAN BARTOLOME APOSTOL CENTRO MEDICO | C124: PABON POLANIA ANTONIO MARIA | D124: KR 59 A # 129 B 01 | E124: 2538825 - 3152059917 - 3114988063 | F124: asociacionsanbartolomeapostol@gmail.com | H124: A · Lista (gerente+email) | I124: Email | J124: Por contactar
A125: 1100108995 | B125: ASOCIACIÓN PROFAMILIA | C125: BUITRAGO RUIZ JAIME | D125: CALLE 34 # 14 52 | E125: (601)4434000 | F125: jonathan.vargas@profamilia.org.co | G125: www.profamilia.org.co | H125: A · Lista (gerente+email) | I125: Email | J125: Por contactar
A126: 1100103183 | B126: ASOCIADOS EN REPRODUCCION HUMANA SAS | C126: CUBILLOS GARCIA MARY JEANNETTE | D126: CL 134 # 7 B 83 CS 708 | E126: (601) 7440055 - 3103440493- 3144443278 | F126: jeancubi1@gmail.com | H126: A · Lista (gerente+email) | I126: Email | J126: Por contactar
A127: 1100109859 | B127: ASOCIADOS UNIDAD NACIONAL ODONTOLOGICA A UNO LTDA | C127: ORTIZ RODRIGUEZ LUIS FERNANDO | D127: AC 53 # 59 03 | E127: 2220297 | F127: aunodentalcolor@hotmail.com | H127: A · Lista (gerente+email) | I127: Email | J127: Por contactar
A128: 1100104870 | B128: ASONEST SAS | C128: PARRA CORREDOR GERMAN DIOGENES | D128: Avenida Calle 127 21 60 Consultorio 218-219 | E128: 6158788 | F128: gerente@asonest.org | G128: www.asonest.org | H128: A · Lista (gerente+email) | I128: Email | J128: Por contactar
A129: 110010487001 | B129: ASONEST SAS CONSULTORIO 218 219 | C129: GINO LEON BELLO RODRIGUEZ | D129: Avenida Calle 127 # 21 60 Consultorio 218 219 | F129: gerente@asonest.org | H129: A · Lista (gerente+email) | I129: Email | J129: Por contactar
A130: 110012627901 | B130: ASSO LTDA ASESORIAS Y SERVICIOS EN SALUD OCUPACIONAL | C130: FERNANDO DURAN BARRERA | D130: CALLE 123 N. 7 - 51 CONSULTORIO 1102 | E130: 6012873029 3002038277 | F130: saludocupacional@assoltda.com | H130: A · Lista (gerente+email) | I130: Email | J130: Por contactar
A131: 110012509501 | B131: ATECHDENTAL SAS | C131: CONSUELO ZAMBRANO BELTRAN | D131: CRA 14 No. 93 - 40 OFICINAS 203-204 | E131: 601-2365716 - 3017156903 | F131: atechdental@hotmail.com | H131: A · Lista (gerente+email) | I131: Email | J131: Por contactar
A132: 110010426107 | B132: ATENCION PRIORITARIA CLINICA COLOMBIA | C132: ADELINA SANCHEZ PULIDO | D132: CL 23 # 66 46 IN 4 CS 516 Y 520 | E132: 7455560-3118980208 | F132: contabilidad@ieco.com.co | H132: A · Lista (gerente+email) | I132: Email | J132: Por contactar
A133: 110013069601 | B133: ATENCIÓN EN MEDICINA LABORAL SAS - SIGLA: ATMELA | C133: ROLANDO MELO RIAÑO | D133: CL 97 # 23 37 PI 7 CS 720 PI 2 CS 205 | E133: 3164740633 | F133: gerencia.atmela@gmail.com | H133: A · Lista (gerente+email) | I133: Email | J133: Por contactar
A134: 1100117354 | B134: ATRYS COLOMBIA S.A.S. | C134: FERNANDO LEON MEDINA MONSALVE | D134: Av Calle 116 # 9-72 Consultorio 410 | E134: 7444187 / 5806969 | F134: sistemadecalidad-co@atryshealth.com | G134: www.atryscolombia.com | H134: A · Lista (gerente+email) | I134: Email | J134: Por contactar
A135: 110011735403 | B135: ATRYS COLOMBIA SAS | C135: JUAN DANIEL SERRANO SANIN | D135: Avenida Carrera 15 88 64 Oficina 804 Edificio Zimma P.H. | E135: 3162417338 | F135: sistemadecalidad-co@atryshealth.com | H135: A · Lista (gerente+email) | I135: Email | J135: Por contactar
A136: 110012134001 | B136: AUDIFONOS ALCIRA RAMIREZ SAS | C136: CARMEN ALCIRA RAMIREZ GALLO | D136: CL. 63 # 11-45 OF. 209 y 213 | E136: 2550054 | F136: ventas@audifonosalcira.com | H136: A · Lista (gerente+email) | I136: Email | J136: Por contactar
A137: 110013938401 | B137: AUDIMEDIC CRC | C137: MAICOL GUTIERREZ MOSQUERA | D137: TRANSVERSAL 18 BIS 14 A 21 SUR LC 1 | E137: 3214327376 | F137: audimediccrc@gmail.com | H137: A · Lista (gerente+email) | I137: Email | J137: Por contactar
A138: 110011604401 | B138: AUDIOCOM BOGOTA | C138: JAIRO DIEGO PORTILLA TORO | D138: Carrera 19 C 90-59 | E138: (1) 742 09 04 - 3174374863 | F138: servicio@audiocom.com.co | H138: A · Lista (gerente+email) | I138: Email | J138: Por contactar
A139: 1100116044 | B139: AUDIOCOM SAS | C139: DIEGO PORTILLA TORO | D139: Carrera 19 C 90-59 | E139: (1) 742 09 04 - 3174374863 | F139: servicio@audiocom.com.co | G139: www.audiocom-ips.com | H139: A · Lista (gerente+email) | I139: Email | J139: Por contactar
A140: 1100119125 | B140: AUDIOSALUD INTEGRAL SAS | C140: CESAR JOVANY MONTAÑO GOMEZ | D140: TV 21 47 76 | E140: 3404777 | F140: calidad@audiosaludintegral.com | G140: WWW.AUDIOSALUDINTEGRAL.COM | H140: A · Lista (gerente+email) | I140: Email | J140: Por contactar
A141: 110012906001 | B141: AUNARSALUD SERVICIOS INTEGRALES EN SALUD SAS - SIGLA AUNARSALUD | C141: JENNY DEL PILAR MARROQUIN PALACIO | D141: CALLE 63 Nº 13-34/12 TORRE A PISO 2 Y 6, TORRE B PISO 2,5,6 | E141: 3206164968 | F141: gerencia@aunarsalud.com | H141: A · Lista (gerente+email) | I141: Email | J141: Por contactar
A142: 110014210504 | B142: AURAL CENTROS AUDITIVOS JAVERIANA | C142: acorrales@widexcolombia.com | D142: CARRERA 7 N 45-10 LOCAL 3 | E142: 7450796-310 4188170 | F142: acorrales@widexcolombia.com | H142: A · Lista (gerente+email) | I142: Email | J142: Por contactar
A143: 110014210502 | B143: AURAL CENTROS AUDITIVOS PLAZA CENTRAL | C143: ANGELICA MARIA CORRALES BETANCOURT | D143: CR. 65 # 11-50 LC 2-50 | E143: 3177640045 | F143: acorrales@widexcolombia.com | H143: A · Lista (gerente+email) | I143: Email | J143: Por contactar
A144: 110012433101 | B144: AURAL CENTROS AUDITIVOS PROFESIONALES | C144: ANGÉLICA MARÍA CORRALES BETANCOURT | D144: KR 7 # 119 - 50 PRIMER PISO | E144: 7450796-310 4188170 | F144: acorrales@widexcolombia.com | H144: A · Lista (gerente+email) | I144: Email | J144: Por contactar
A145: 110012433102 | B145: AURAL JAVERIANA | C145: JESUS THOMAS HERRERA LOPEZ | D145: CARRERA 7 N 45-10 LOCAL 3 | E145: 7450796-310 4188170 | F145: acorrales@widexcolombia.com | H145: A · Lista (gerente+email) | I145: Email | J145: Por contactar
A146: 110013935501 | B146: AUTOIMMUNITY S.A.S SIGLA AUTOIMMUNITY | C146: MARTHA CATALINA ROJAS GUTIERREZ | D146: Cl 99 # 49 38 CS 1109 | E146: 3057367025 | F146: laboratorioautoimmunity@gmail.com | H146: A · Lista (gerente+email) | I146: Email | J146: Por contactar
A147: 110012043601 | B147: AVAMED DIAGNOSTICO MEDICO S.A.S / SIGLA: AVAMED S.A.S | C147: CAROL MELISA OLEJUA OLARTE | D147: AVENIDA CARRERA 72 NO. 50 - 37 | E147: 3202780872-3208705323-3136864136 | F147: gerencia@diagnosticomedico.co | H147: A · Lista (gerente+email) | I147: Email | J147: Por contactar
A148: 110012236601 | B148: AVANCES TERAPEUTICOS IPS SAS | C148: cesar Guiovanni Mendoza Vargas | D148: Avenida Carrera 24 no 84-40 LOCAL 101 | E148: 7468830 | F148: avanceterapeutico@gmail.com | H148: A · Lista (gerente+email) | I148: Email | J148: Por contactar
A149: 110013054401 | B149: AVANT SALUD INTEGRAL SAS | C149: Kelly Vasquez Gamboa | D149: CL 150 # 16-56 OF 3008 | E149: 3108797814-3114570187 | F149: avantsaludintegral@gmail.com | H149: A · Lista (gerente+email) | I149: Email | J149: Por contactar
A150: 110013054402 | B150: AVANT SALUD INTEGRAL SEDE GALERIAS | C150: KELLY JOHANNA VASQUEZ GAMBOA | D150: CALLE 53 B 25 21 OFICINA 2226 | E150: 3187244576 | F150: avantsaludintegral.galerias@gmail.com | H150: A · Lista (gerente+email) | I150: Email | J150: Por contactar
A151: 110012742603 | B151: AVANZAR IPS REHABILITACIÓN Y HABILITACIÓN SAS | C151: JOSE ANDRES REYES CARVAJAL | D151: CALLE 18 A SUR # 29B - 79 PISO 1 | E151: 3143906508 | F151: ipsavanzar@gmail.com | H151: A · Lista (gerente+email) | I151: Email | J151: Por contactar
A152: 110014210601 | B152: AVEMI SAS | C152: ADRIANA DEL PILAR VENEGAS MORTIGO | D152: Cl 119 No 14-42 Cs 301-303-304 | E152: 3204449827 | F152: admin@adrianavenegas.com | H152: A · Lista (gerente+email) | I152: Email | J152: Por contactar
A153: 1100120538 | B153: AVENIR SALUD SAS | C153: Marta Luz Bernal Camacho | D153: Cl 50 Nº 8-24 CS 305 | E153: 7026887-3103183025- 7027086 | F153: martaluz@avenirsalud.com | G153: WWW.avenirsalud.com | H153: A · Lista (gerente+email) | I153: Email | J153: Por contactar
A154: 1100111138 | B154: AXA ASISTENCIA IPS SAS | C154: RAOCH MICHAELS INGRID VIVIANA | D154: Carrera 14 #98-95 Consultorio 303 edificio chico 99 | E154: 6446156 | F154: AXAIPS@AXA-ASSISTANCE.COM.CO | H154: A · Lista (gerente+email) | I154: Email | J154: Por contactar
...
