Workbook

Sheet Tablero semanal
A1: Tablero · avance hacia USD 100K MRR
A4: Semanas con datos | B4: =COUNT('Avance semanal'!D5:D30) -> 0
A5: MRR actual | B5: =IFERROR(LOOKUP(2,1/('Avance semanal'!$D$5:$D$30<>""),'Avance semanal'!$D$5:$D$30),Supuestos!B7) -> 20000
A6: Plan a la fecha | B6: =IFERROR(LOOKUP(2,1/('Avance semanal'!$D$5:$D$30<>""),'Avance semanal'!$C$5:$C$30),Supuestos!B7) -> 20000
A7: vs Plan | B7: =B5-B6 -> 0
A8: % de la meta (100K) | B8: =B5/Supuestos!B8 -> 0.2
A9: WoW real (última) | B9: =IFERROR(LOOKUP(2,1/('Avance semanal'!$G$5:$G$30<>""),'Avance semanal'!$G$5:$G$30),"")
A10: WoW requerido (YC) | B10: ='Rampa 6 meses (YC)'!B3 -> 0.063857505
A11: Cierres acum reales | B11: =SUM('Avance semanal'!L5:L30) -> 0
A12: Cierres plan a la fecha | B12: =IFERROR(LOOKUP(2,1/('Avance semanal'!$D$5:$D$30<>""),'Avance semanal'!$H$5:$H$30),0) -> 0
A14: Estado general | B14: =IF(B4=0,"Sin datos",IF(B5>=B6,"EN META",IF(B5>=0.9*B6,"VIGILAR","ATRASADO"))) -> Sin datos
A16: Cómo usarlo
A17: • Cada lunes, ve a la hoja "Avance semanal" y llena las celdas azules/amarillas: MRR real y cierres por motor.
A18: • Este tablero y la gráfica se actualizan solos.
A19: • El semáforo compara tu MRR real contra el plan de esa semana (verde = en meta, amarillo = a <10%, rojo = atrasado).
A20: • Si el plan cambia, ajusta los supuestos en la hoja "Supuestos" — sobre todo el MRR inicial (B7).

Sheet Aliados — resumen
A1: Canal aliados — migración a Fail Fast
A3: Aliado | B3: Empresas | C3: MRR potencial | D3: Conversión sem | E3: Empresas migradas | F3: MRR semestre
A4: Simba | B4: ='Simba (aliado)'!B15 -> 159 | C4: ='Simba (aliado)'!D15 -> 24243 | D4: ='Simba (aliado)'!B8 -> 0.6 | E4: =ROUND(B4*D4,0) -> 95 | F4: =C4*D4 -> 14545.8
A5: SAO | B5: ='SAO (aliado)'!C16 -> 0 | C5: ='SAO (aliado)'!E16 -> 0 | D5: ='SAO (aliado)'!B8 -> 0.6 | E5: =ROUND(B5*D5,0) -> 0 | F5: =C5*D5 -> 0
A6: Total | B6: =SUM(B4:B5) -> 159 | E6: =SUM(E4:E5) -> 95 | F6: =SUM(F4:F5) -> 14545.8
A8: Cómo suma al plan
A9: • Este canal lo ejecuta el aliado (Simba/SAO), en paralelo a la venta directa de Fail Fast.
A10: • El MRR semestre de aliados se suma al Puente a 100K (fila "Migración aliados").
A11: • Simba = related-party (socio de Fail Fast). El ingreso por documentos electrónicos NO es de Fail Fast: queda en Simba.
A12: • Fail Fast solo factura el ERP ($/usuario). La migración es base caliente → conversión alta esperada.

Sheet Resumen
A1: Plan del semestre · tablero
A3: North Star · Meta MRR | B3: =Supuestos!B8 -> 100000
A4: MRR inicial (actualizar) | B4: =Supuestos!B7 -> 20000
A5: WoW requerido (YC) | B5: ='Rampa 6 meses (YC)'!B3 -> 0.063857505
A6: Cierres/mes | B6: ='Puente a 100K'!B9/Supuestos!B5 -> 28.333333
A7: Total nuevos logos | B7: ='Puente a 100K'!B9 -> 170
A8: CAC mezclado (pond.) | B8: ='Unit economics'!B7 -> 704.17647
A9: NRR objetivo | B9: =Supuestos!B43 -> 1.15
A10: Churn logo mensual | B10: =Supuestos!B42 -> 0.03
A11: Plan bottom-up (semestre) | B11: ='Puente a 100K'!D9 -> 77885.8
A12: Cómo leer el modelo
A13: • Azul = supuesto editable. Amarillo = perilla clave del board.
A14: • Verde = enlace a la hoja Supuestos. Negro = fórmula.
A15: • Cambia un supuesto y todo el modelo recalcula.
A16: • Las 3 perillas más sensibles: MRR inicial, % sobre ERP global, churn.

Sheet Supuestos
A1: Supuestos · perillas del modelo
A3: Globales
A4: FX (COP/USD) | B4: 4000 | C4: COP
A5: Horizonte | B5: 6 | C5: meses
A6: Semanas en el horizonte | B6: 26 | C6: sem
A7: MRR inicial (USD) | B7: 20000 | C7: USD | D7: REEMPLAZAR con el MRR real de hoy
A8: Meta MRR (USD) | B8: 100000 | C8: USD | D8: La única North Star del semestre
A10: Conversión de embudo
A11: Cold · contacto → reunión | B11: 0.05
A12: Cold · reunión → oportunidad | B12: 0.4
A13: Cold · oportunidad → cierre | B13: 0.6
A14: Gremio · asistente → reunión | B14: 0.25 | D14: luego usa las mismas etapas reunión→oport→cierre
A15: ABM · cuenta → cierre | B15: 0.28 | D15: motion de cuentas grandes (viernes en sitio)
A17: Motor 1 · Grandes
A18: Universo Grandes Contribuyentes | B18: 2650 | C18: emp | D18: DIAN Res. 000200/2024, ajuste 248/2025
A19: % sobre ERP global (SAP/Oracle/…) | B19: 0.55 | D19: perilla del board
A20: % con volumen CxP material | B20: 0.8 | D20: perilla del board
A21: Cierres land (agente CxP) | B21: 40 | C21: log
A22: MRR/u land | B22: 400 | C22: USD
A23: Cierres expand ERP (próximo año · informativo) | B23: 10 | C23: log | D23: Fuera del puente del semestre — cuentas SAP no migran ERP en 6 meses
A24: MRR/u expand | B24: 3833 | C24: USD
A25: CAC Grandes (agente) | B25: 827 | C25: USD
A27: Motor 2 · Transporte
A28: SAM (carga, 10+ usuarios) | B28: 825 | C28: emp | D28: base RNDC / MinTransporte
A29: Cierres objetivo | B29: 20 | C29: log
A30: MRR/u | B30: 992 | C30: USD
A31: CAC | B31: 650 | C31: USD
A33: Motor 3 · Salud IPS N1
A34: SAM (IPS Nivel 1) | B34: 4000 | C34: emp | D34: base REPS / ACHC
A35: Cierres objetivo | B35: 15 | C35: log
A36: MRR/u | B36: 1500 | C36: USD
A37: CAC | B37: 367 | C37: USD
A39: Expansión y unit economics
A40: MRR expansión / NRR | B40: 5000 | C40: USD
A41: Margen bruto SaaS | B41: 0.75
A42: Churn logo mensual | B42: 0.03 | D42: perilla del board
A43: NRR objetivo | B43: 1.15

Sheet Puente a 100K
A1: El puente a USD 100K MRR
A3: Segmento | B3: Nuevos logos | C3: MRR/u | D3: MRR | E3: % del total
A4: IPS Nivel 1 | B4: =Supuestos!B35 -> 15 | C4: =Supuestos!B36 -> 1500 | D4: =B4*C4 -> 22500 | E4: =D4/$D$9 -> 0.2888845
A5: Transporte TMS | B5: =Supuestos!B29 -> 20 | C5: =Supuestos!B30 -> 992 | D5: =B5*C5 -> 19840 | E5: =D5/$D$9 -> 0.25473193
A6: Grandes — agente CxP (land) | B6: =Supuestos!B21 -> 40 | C6: =Supuestos!B22 -> 400 | D6: =B6*C6 -> 16000 | E6: =D6/$D$9 -> 0.20542897
A7: Expansión (NRR) | B7: — | C7: — | D7: =Supuestos!B40 -> 5000 | E7: =D7/$D$9 -> 0.064196554
A8: Migración aliados (Simba+SAO) | B8: ='Aliados — resumen'!E6 -> 95 | C8: — | D8: ='Aliados — resumen'!F6 -> 14545.8 | E8: =D8/$D$9 -> 0.18675805
A9: Plan total (semestre) | B9: =SUM(B4:B6)+B8 -> 170 | D9: =SUM(D4:D8) -> 77885.8 | E9: =D9/$D$9 -> 1
A11: Meta · North Star | D11: =Supuestos!B8 -> 100000
A12: Brecha vs meta | D12: =D11-D9 -> 22114.2
A13: % de la meta cubierto | D13: =D9/D11 -> 0.778858
A15: Para cerrar la brecha (sin ERP)
A16: Precio agente req. (con 40 lands) | D16: =(D11-D4-D5-D7)/Supuestos!B21 -> 1316.5 | E16: vs $400 hoy
A17: Lands req. (a $400/mes) | D17: =(D11-D4-D5-D7)/Supuestos!B22 -> 131.65 | E17: vs 40 hoy
A19: Pipeline próximo año (NO cuenta este semestre)
A20: Grandes — expand a ERP multi-entidad | B20: =Supuestos!B23 -> 10 | C20: =Supuestos!B24 -> 3833 | D20: =B20*C20 -> 38330 | E20: próximo año

Sheet Embudo por motor
A1: Embudo: cuántas hay → a cuántas bajo → cómo
A3: Motor | B3: SAM | C3: Cierres | D3: Penetración | E3: Motion | F3: Contactos/cuentas necesarios | G3: Nota
A4: 1 · Grandes | B4: =Supuestos!B18*Supuestos!B19*Supuestos!B20 -> 1166 | C4: =Supuestos!B21 -> 40 | D4: =C4/B4 -> 0.034305317 | E4: ABM viernes en sitio | F4: =C4/Supuestos!B15 -> 142.85714 | G4: cuentas trabajadas (solo agente; ERP = próximo año)
A5: 2 · Transporte | B5: =Supuestos!B28 -> 825 | C5: =Supuestos!B29 -> 20 | D5: =C5/B5 -> 0.024242424 | E5: Gremio (taller) | F5: =C5/(Supuestos!B14*Supuestos!B12*Supuestos!B13) -> 333.33333 | G5: asistentes; en frío 1,667 > SAM → imposible
A6: 3 · Salud IPS N1 | B6: =Supuestos!B34 -> 4000 | C6: =Supuestos!B35 -> 15 | D6: =C6/B6 -> 0.00375 | E6: Gremio (taller) | F6: =C6/(Supuestos!B14*Supuestos!B12*Supuestos!B13) -> 250 | G6: asistentes; cuello = implementación
A8: Frío ≈ 83 contactos/cierre · Gremio ≈ 17 asistentes/cierre · ABM ≈ 1/0.28 cuentas/cierre

Sheet Unit economics
A1: Unit economics por segmento
A3: Segmento | B3: CAC | C3: MRR/u | D3: Margen | E3: GP mensual | F3: Payback | G3: LTV | H3: LTV:CAC
A4: IPS Nivel 1 | B4: =Supuestos!B37 -> 367 | C4: =Supuestos!B36 -> 1500 | D4: =Supuestos!B41 -> 0.75 | E4: =C4*D4 -> 1125 | F4: =B4/E4 -> 0.32622222 | G4: =E4/Supuestos!B42 -> 37500 | H4: =G4/B4 -> 102.17984
A5: Transporte TMS | B5: =Supuestos!B31 -> 650 | C5: =Supuestos!B30 -> 992 | D5: =Supuestos!B41 -> 0.75 | E5: =C5*D5 -> 744 | F5: =B5/E5 -> 0.87365591 | G5: =E5/Supuestos!B42 -> 24800 | H5: =G5/B5 -> 38.153846
A6: Grandes (agente) | B6: =Supuestos!B25 -> 827 | C6: =Supuestos!B22 -> 400 | D6: =Supuestos!B41 -> 0.75 | E6: =C6*D6 -> 300 | F6: =B6/E6 -> 2.7566667 | G6: =E6/Supuestos!B42 -> 10000 | H6: =G6/B6 -> 12.091898
A7: Mezclado (pond. por logos) | B7: =(Supuestos!B35*Supuestos!B37+Supuestos!B29*Supuestos!B31+(Supuestos!B21+Supuestos!B23)*Supuestos!B25)/(Supuestos!B35+Supuestos!B29+Supuestos!B21+Supuestos!B23) -> 704.17647
A9: LTV = GP mensual ÷ churn mensual. Ratios muy altos → el límite es throughput/capacidad, no eficiencia. Payback en semanas.

Sheet Rampa 6 meses (YC)
A1: Rampa a 100K · tasa de crecimiento YC
A3: WoW requerido (YC growth rate) | B3: =(Supuestos!B8/Supuestos!B7)^(1/Supuestos!B6)-1 -> 0.063857505 | C3: objetivo 5–7%
A4: MoM requerido | B4: =(Supuestos!B8/Supuestos!B7)^(1/Supuestos!B5)-1 -> 0.30766049
A5: Cierres/mes (cadencia) | B5: ='Puente a 100K'!B9/Supuestos!B5 -> 28.333333
A6: MRR nuevo por logo (prom.) | B6: =(('Puente a 100K'!D9-Supuestos!B40))/'Puente a 100K'!B9 -> 428.74
A8: Mes | B8: MRR objetivo | C8: MRR nuevo | D8: Cierres del mes | E8: Acumulado logos | F8: % de la meta
A9: 0 | B9: =Supuestos!B7 -> 20000 | F9: =B9/Supuestos!B8 -> 0.2
A10: 1 | B10: =Supuestos!$B$7*(1+$B$4)^A10 -> 26153.21 | C10: =B10-B9 -> 6153.2097 | D10: =C10/$B$6 -> 14.351844 | E10: =SUM($D$10:D10) -> 14.351844 | F10: =B10/Supuestos!$B$8 -> 0.2615321
A11: 2 | B11: =Supuestos!$B$7*(1+$B$4)^A11 -> 34199.519 | C11: =B11-B10 -> 8046.3092 | D11: =C11/$B$6 -> 18.76734 | E11: =SUM($D$10:D11) -> 33.119184 | F11: =B11/Supuestos!$B$8 -> 0.34199519
A12: 3 | B12: =Supuestos!$B$7*(1+$B$4)^A12 -> 44721.36 | C12: =B12-B11 -> 10521.841 | D12: =C12/$B$6 -> 24.541309 | E12: =SUM($D$10:D12) -> 57.660492 | F12: =B12/Supuestos!$B$8 -> 0.4472136
A13: 4 | B13: =Supuestos!$B$7*(1+$B$4)^A13 -> 58480.355 | C13: =B13-B12 -> 13758.995 | D13: =C13/$B$6 -> 32.091699 | E13: =SUM($D$10:D13) -> 89.752192 | F13: =B13/Supuestos!$B$8 -> 0.58480355
A14: 5 | B14: =Supuestos!$B$7*(1+$B$4)^A14 -> 76472.449 | C14: =B14-B13 -> 17992.094 | D14: =C14/$B$6 -> 41.965047 | E14: =SUM($D$10:D14) -> 131.71724 | F14: =B14/Supuestos!$B$8 -> 0.76472449
A15: 6 | B15: =Supuestos!$B$7*(1+$B$4)^A15 -> 100000 | C15: =B15-B14 -> 23527.551 | D15: =C15/$B$6 -> 54.876034 | E15: =SUM($D$10:D15) -> 186.59327 | F15: =B15/Supuestos!$B$8 -> 1
A17: Baja el MRR inicial (Supuestos!B7) y sube el WoW requerido. Con 20K→100K en 26 sem ≈ 6.4% WoW.

Sheet Avance semanal
A1: Avance semanal · captura
A2: Ingresa cada lunes: MRR real y cierres por motor (celdas azules). El resto se calcula solo.
A4: Sem | B4: Fecha | C4: Plan MRR | D4: MRR real ← | E4: Var MRR | F4: % meta | G4: WoW real | H4: Plan cierres | I4: IPS ← | J4: Transp ← | K4: Grandes ← | L4: Cierres sem | M4: Cierres acum | N4: Var cierres | O4: Estado
A5: 1 | C5: =Supuestos!$B$7*(1+'Rampa 6 meses (YC)'!$B$3)^A5 -> 21277.15 | E5: =IF(D5="","",D5-C5) | F5: =IF(D5="","",D5/Supuestos!$B$8) | G5: =IF(OR(D5="",Supuestos!$B$7=""),"",D5/Supuestos!$B$7-1) | H5: =ROUND((C5-Supuestos!$B$7)/(Supuestos!$B$8-Supuestos!$B$7)*'Puente a 100K'!$B$9,1) -> 2.7 | L5: =SUM(I5:K5) -> 0 | M5: =IF(D5="","",SUM($L$5:L5)) | N5: =IF(D5="","",M5-H5) | O5: =IF(D5="","",IF(D5>=C5,"En meta",IF(D5>=0.9*C5,"Vigilar","Atrasado")))
A6: 2 | C6: =Supuestos!$B$7*(1+'Rampa 6 meses (YC)'!$B$3)^A6 -> 22635.856 | E6: =IF(D6="","",D6-C6) | F6: =IF(D6="","",D6/Supuestos!$B$8) | G6: =IF(OR(D6="",D5=""),"",D6/D5-1) | H6: =ROUND((C6-Supuestos!$B$7)/(Supuestos!$B$8-Supuestos!$B$7)*'Puente a 100K'!$B$9,1) -> 5.6 | L6: =SUM(I6:K6) -> 0 | M6: =IF(D6="","",SUM($L$5:L6)) | N6: =IF(D6="","",M6-H6) | O6: =IF(D6="","",IF(D6>=C6,"En meta",IF(D6>=0.9*C6,"Vigilar","Atrasado")))
A7: 3 | C7: =Supuestos!$B$7*(1+'Rampa 6 meses (YC)'!$B$3)^A7 -> 24081.325 | E7: =IF(D7="","",D7-C7) | F7: =IF(D7="","",D7/Supuestos!$B$8) | G7: =IF(OR(D7="",D6=""),"",D7/D6-1) | H7: =ROUND((C7-Supuestos!$B$7)/(Supuestos!$B$8-Supuestos!$B$7)*'Puente a 100K'!$B$9,1) -> 8.7 | L7: =SUM(I7:K7) -> 0 | M7: =IF(D7="","",SUM($L$5:L7)) | N7: =IF(D7="","",M7-H7) | O7: =IF(D7="","",IF(D7>=C7,"En meta",IF(D7>=0.9*C7,"Vigilar","Atrasado")))
A8: 4 | C8: =Supuestos!$B$7*(1+'Rampa 6 meses (YC)'!$B$3)^A8 -> 25619.098 | E8: =IF(D8="","",D8-C8) | F8: =IF(D8="","",D8/Supuestos!$B$8) | G8: =IF(OR(D8="",D7=""),"",D8/D7-1) | H8: =ROUND((C8-Supuestos!$B$7)/(Supuestos!$B$8-Supuestos!$B$7)*'Puente a 100K'!$B$9,1) -> 11.9 | L8: =SUM(I8:K8) -> 0 | M8: =IF(D8="","",SUM($L$5:L8)) | N8: =IF(D8="","",M8-H8) | O8: =IF(D8="","",IF(D8>=C8,"En meta",IF(D8>=0.9*C8,"Vigilar","Atrasado")))
A9: 5 | C9: =Supuestos!$B$7*(1+'Rampa 6 meses (YC)'!$B$3)^A9 -> 27255.07 | E9: =IF(D9="","",D9-C9) | F9: =IF(D9="","",D9/Supuestos!$B$8) | G9: =IF(OR(D9="",D8=""),"",D9/D8-1) | H9: =ROUND((C9-Supuestos!$B$7)/(Supuestos!$B$8-Supuestos!$B$7)*'Puente a 100K'!$B$9,1) -> 15.4 | L9: =SUM(I9:K9) -> 0 | M9: =IF(D9="","",SUM($L$5:L9)) | N9: =IF(D9="","",M9-H9) | O9: =IF(D9="","",IF(D9>=C9,"En meta",IF(D9>=0.9*C9,"Vigilar","Atrasado")))
A10: 6 | C10: =Supuestos!$B$7*(1+'Rampa 6 meses (YC)'!$B$3)^A10 -> 28995.511 | E10: =IF(D10="","",D10-C10) | F10: =IF(D10="","",D10/Supuestos!$B$8) | G10: =IF(OR(D10="",D9=""),"",D10/D9-1) | H10: =ROUND((C10-Supuestos!$B$7)/(Supuestos!$B$8-Supuestos!$B$7)*'Puente a 100K'!$B$9,1) -> 19.1 | L10: =SUM(I10:K10) -> 0 | M10: =IF(D10="","",SUM($L$5:L10)) | N10: =IF(D10="","",M10-H10) | O10: =IF(D10="","",IF(D10>=C10,"En meta",IF(D10>=0.9*C10,"Vigilar","Atrasado")))
A11: 7 | C11: =Supuestos!$B$7*(1+'Rampa 6 meses (YC)'!$B$3)^A11 -> 30847.092 | E11: =IF(D11="","",D11-C11) | F11: =IF(D11="","",D11/Supuestos!$B$8) | G11: =IF(OR(D11="",D10=""),"",D11/D10-1) | H11: =ROUND((C11-Supuestos!$B$7)/(Supuestos!$B$8-Supuestos!$B$7)*'Puente a 100K'!$B$9,1) -> 23.1 | L11: =SUM(I11:K11) -> 0 | M11: =IF(D11="","",SUM($L$5:L11)) | N11: =IF(D11="","",M11-H11) | O11: =IF(D11="","",IF(D11>=C11,"En meta",IF(D11>=0.9*C11,"Vigilar","Atrasado")))
A12: 8 | C12: =Supuestos!$B$7*(1+'Rampa 6 meses (YC)'!$B$3)^A12 -> 32816.91 | E12: =IF(D12="","",D12-C12) | F12: =IF(D12="","",D12/Supuestos!$B$8) | G12: =IF(OR(D12="",D11=""),"",D12/D11-1) | H12: =ROUND((C12-Supuestos!$B$7)/(Supuestos!$B$8-Supuestos!$B$7)*'Puente a 100K'!$B$9,1) -> 27.2 | L12: =SUM(I12:K12) -> 0 | M12: =IF(D12="","",SUM($L$5:L12)) | N12: =IF(D12="","",M12-H12) | O12: =IF(D12="","",IF(D12>=C12,"En meta",IF(D12>=0.9*C12,"Vigilar","Atrasado")))
A13: 9 | C13: =Supuestos!$B$7*(1+'Rampa 6 meses (YC)'!$B$3)^A13 -> 34912.516 | E13: =IF(D13="","",D13-C13) | F13: =IF(D13="","",D13/Supuestos!$B$8) | G13: =IF(OR(D13="",D12=""),"",D13/D12-1) | H13: =ROUND((C13-Supuestos!$B$7)/(Supuestos!$B$8-Supuestos!$B$7)*'Puente a 100K'!$B$9,1) -> 31.7 | L13: =SUM(I13:K13) -> 0 | M13: =IF(D13="","",SUM($L$5:L13)) | N13: =IF(D13="","",M13-H13) | O13: =IF(D13="","",IF(D13>=C13,"En meta",IF(D13>=0.9*C13,"Vigilar","Atrasado")))
A14: 10 | C14: =Supuestos!$B$7*(1+'Rampa 6 meses (YC)'!$B$3)^A14 -> 37141.942 | E14: =IF(D14="","",D14-C14) | F14: =IF(D14="","",D14/Supuestos!$B$8) | G14: =IF(OR(D14="",D13=""),"",D14/D13-1) | H14: =ROUND((C14-Supuestos!$B$7)/(Supuestos!$B$8-Supuestos!$B$7)*'Puente a 100K'!$B$9,1) -> 36.4 | L14: =SUM(I14:K14) -> 0 | M14: =IF(D14="","",SUM($L$5:L14)) | N14: =IF(D14="","",M14-H14) | O14: =IF(D14="","",IF(D14>=C14,"En meta",IF(D14>=0.9*C14,"Vigilar","Atrasado")))
A15: 11 | C15: =Supuestos!$B$7*(1+'Rampa 6 meses (YC)'!$B$3)^A15 -> 39513.734 | E15: =IF(D15="","",D15-C15) | F15: =IF(D15="","",D15/Supuestos!$B$8) | G15: =IF(OR(D15="",D14=""),"",D15/D14-1) | H15: =ROUND((C15-Supuestos!$B$7)/(Supuestos!$B$8-Supuestos!$B$7)*'Puente a 100K'!$B$9,1) -> 41.5 | L15: =SUM(I15:K15) -> 0 | M15: =IF(D15="","",SUM($L$5:L15)) | N15: =IF(D15="","",M15-H15) | O15: =IF(D15="","",IF(D15>=C15,"En meta",IF(D15>=0.9*C15,"Vigilar","Atrasado")))
A16: 12 | C16: =Supuestos!$B$7*(1+'Rampa 6 meses (YC)'!$B$3)^A16 -> 42036.983 | E16: =IF(D16="","",D16-C16) | F16: =IF(D16="","",D16/Supuestos!$B$8) | G16: =IF(OR(D16="",D15=""),"",D16/D15-1) | H16: =ROUND((C16-Supuestos!$B$7)/(Supuestos!$B$8-Supuestos!$B$7)*'Puente a 100K'!$B$9,1) -> 46.8 | L16: =SUM(I16:K16) -> 0 | M16: =IF(D16="","",SUM($L$5:L16)) | N16: =IF(D16="","",M16-H16) | O16: =IF(D16="","",IF(D16>=C16,"En meta",IF(D16>=0.9*C16,"Vigilar","Atrasado")))
A17: 13 | C17: =Supuestos!$B$7*(1+'Rampa 6 meses (YC)'!$B$3)^A17 -> 44721.36 | E17: =IF(D17="","",D17-C17) | F17: =IF(D17="","",D17/Supuestos!$B$8) | G17: =IF(OR(D17="",D16=""),"",D17/D16-1) | H17: =ROUND((C17-Supuestos!$B$7)/(Supuestos!$B$8-Supuestos!$B$7)*'Puente a 100K'!$B$9,1) -> 52.5 | L17: =SUM(I17:K17) -> 0 | M17: =IF(D17="","",SUM($L$5:L17)) | N17: =IF(D17="","",M17-H17) | O17: =IF(D17="","",IF(D17>=C17,"En meta",IF(D17>=0.9*C17,"Vigilar","Atrasado")))
... A30: 26 | C30: =Supuestos!$B$7*(1+'Rampa 6 meses (YC)'!$B$3)^A30 -> 100000 | E30: =IF(D30="","",D30-C30) | F30: =IF(D30="","",D30/Supuestos!$B$8) | G30: =IF(OR(D30="",D29=""),"",D30/D29-1) | H30: =ROUND((C30-Supuestos!$B$7)/(Supuestos!$B$8-Supuestos!$B$7)*'Puente a 100K'!$B$9,1) -> 170 | L30: =SUM(I30:K30) -> 0 | M30: =IF(D30="","",SUM($L$5:L30)) | N30: =IF(D30="","",M30-H30) | O30: =IF(D30="","",IF(D30>=C30,"En meta",IF(D30>=0.9*C30,"Vigilar","Atrasado")))

Sheet Simba (aliado)
A1: Simba — migración a Fail Fast (ERP)
A3: Precios y supuestos
A4: $/usuario · Contabilidad | B4: 49
A5: $/usuario · Salud (HC) | B5: 79
A6: $/usuario · TMS | B6: 99
A7: Usuarios promedio / empresa | B7: 3
A8: Conversión a Fail Fast (semestre) | B8: 0.6
A10: Resumen por tipo
A11: Tipo | B11: Empresas | C11: $/usuario | D11: MRR potencial
A12: Contabilidad | B12: =COUNTIF($D$22:$D$400,"Contabilidad") -> 152 | C12: =$B$4 -> 49 | D12: =SUMIF($D$22:$D$400,"Contabilidad",$G$22:$G$400) -> 22344
A13: Salud | B13: =COUNTIF($D$22:$D$400,"Salud") -> 3 | C13: =$B$5 -> 79 | D13: =SUMIF($D$22:$D$400,"Salud",$G$22:$G$400) -> 711
A14: TMS | B14: =COUNTIF($D$22:$D$400,"TMS") -> 4 | C14: =$B$6 -> 99 | D14: =SUMIF($D$22:$D$400,"TMS",$G$22:$G$400) -> 1188
A15: Total | B15: =SUM(B12:B14) -> 159 | D15: =SUM(D12:D14) -> 24243
A17: MRR semestre (potencial × conversión) | B17: =D15*B8 -> 14545.8
A19: Simba es propiedad de un socio de Fail Fast → canal relacionado (related-party). El ingreso por documentos electrónicos permanece en Simba; Fail Fast solo factura el ERP ($/usuario).
A21: Empresa | B21: Docs total | C21: Docs 2025 | D21: Tipo | E21: Usuarios | F21: $/usuario | G21: MRR
A22: CONCESION SANTA MARTA PARAGUACHON S.A. | B22: 96276 | C22: 96275 | D22: Contabilidad | E22: 3 | F22: =IF(D22="Salud",$B$5,IF(D22="TMS",$B$6,$B$4)) -> 49 | G22: =E22*F22 -> 147
A23: COOPERATIVA DE MOTORISTAS DEL HUILA Y CAQUETA LTDA | B23: 980 | C23: 925 | D23: Contabilidad | E23: 3 | F23: =IF(D23="Salud",$B$5,IF(D23="TMS",$B$6,$B$4)) -> 49 | G23: =E23*F23 -> 147
A24: NATALIA ARENAS | B24: 85 | C24: 65 | D24: Contabilidad | E24: 3 | F24: =IF(D24="Salud",$B$5,IF(D24="TMS",$B$6,$B$4)) -> 49 | G24: =E24*F24 -> 147
A25: ENERGY LIVING S.A.S. | B25: 36 | C25: 13 | D25: Contabilidad | E25: 3 | F25: =IF(D25="Salud",$B$5,IF(D25="TMS",$B$6,$B$4)) -> 49 | G25: =E25*F25 -> 147
A26: JORGE VARON MUNAR | B26: 36 | C26: 11 | D26: Contabilidad | E26: 3 | F26: =IF(D26="Salud",$B$5,IF(D26="TMS",$B$6,$B$4)) -> 49 | G26: =E26*F26 -> 147
A27: BUGANVILO S.A.S | B27: 6 | C27: 2 | D27: Contabilidad | E27: 3 | F27: =IF(D27="Salud",$B$5,IF(D27="TMS",$B$6,$B$4)) -> 49 | G27: =E27*F27 -> 147
A28: SCHWARZIN S.A.S. | B28: 6 | C28: 2 | D28: Contabilidad | E28: 3 | F28: =IF(D28="Salud",$B$5,IF(D28="TMS",$B$6,$B$4)) -> 49 | G28: =E28*F28 -> 147
A29: VERDAU S.A.S. | B29: 4 | C29: 2 | D29: Contabilidad | E29: 3 | F29: =IF(D29="Salud",$B$5,IF(D29="TMS",$B$6,$B$4)) -> 49 | G29: =E29*F29 -> 147
A30: ETAPA 2 LA VIDA ES BELLA S.A.S | B30: 3 | C30: 3 | D30: Contabilidad | E30: 3 | F30: =IF(D30="Salud",$B$5,IF(D30="TMS",$B$6,$B$4)) -> 49 | G30: =E30*F30 -> 147
A31: ETAPA 3 LA VIDA ES BELLA S.A.S | B31: 2 | C31: 2 | D31: Contabilidad | E31: 3 | F31: =IF(D31="Salud",$B$5,IF(D31="TMS",$B$6,$B$4)) -> 49 | G31: =E31*F31 -> 147
A32: JUAN PABLO POSADA ARCINIEGAS | B32: 2 | C32: 1 | D32: Contabilidad | E32: 3 | F32: =IF(D32="Salud",$B$5,IF(D32="TMS",$B$6,$B$4)) -> 49 | G32: =E32*F32 -> 147
A33: INVERSIONES RRM & CIA SAS | B33: 1 | C33: 1 | D33: Contabilidad | E33: 3 | F33: =IF(D33="Salud",$B$5,IF(D33="TMS",$B$6,$B$4)) -> 49 | G33: =E33*F33 -> 147
... A180: PUNTO DE SERVICIOS S.A. | B180: 76629 | C180: 9455 | D180: Contabilidad | E180: 3 | F180: =IF(D180="Salud",$B$5,IF(D180="TMS",$B$6,$B$4)) -> 49 | G180: =E180*F180 -> 147

Sheet TMS
A1: No. | B1: DIRECCIÓN TERRITORIAL | C1: NIT | D1: EMPRESA | E1: RESOLUCIÓN HABILITACIÓN No. | F1: FECHA (DD-MM-AAAA) | G1: RESOLUCIÓN MODIFICACIÓN No. | H1: FECHA MODIFICACIÓN (DD/MM/AAAA) | I1: ESTADO RUES | J1: OBSERVACIONES | K1: PÁGINA WEB | L1: CONTACTO 1 (NOMBRE Y CARGO) | M1: CONTACTO 1 (EMAIL/WHATSAPP) | N1: CONTACTO 2 (NOMBRE Y CARGO) | O1: CONTACTO 2 (EMAIL/WHATSAPP)
A2: 1 | B2: ANTIOQUIA | C2: 811009788 | D2: DISTRACOM CIA LTDA | E2: 47 | F2: 36586 | I2: ACTIVA
A3: 2 | B3: ANTIOQUIA | C3: 890920990 | D3: TRANSPORTES SAFERBO S.A. | E3: 132 | F3: 36656 | I3: ACTIVA
A4: 3 | B4: ANTIOQUIA | C4: 890913002 | D4: TRANSPORTES SUROESTE ANTIOQUEÑO S.A. | E4: 159 | F4: 36665 | I4: ACTIVA
A5: 4 | B5: ANTIOQUIA | C5: 811020940 | D5: COOPERATIVA DE TRANSPORTADORES DEL DARIEN | E5: 280 | F5: 36755 | I5: ACTIVA
A6: 5 | B6: ANTIOQUIA | C6: 890981457 | D6: COOPERATIVA DE TRANSPORTADORES DEL ORIENTE ANTIOQUEÑO LTDA | E6: 372 | F6: 36826 | I6: ACTIVA
A7: 6 | B7: ANTIOQUIA | C7: 800154972 | D7: TRANSPORTES DELFIN LTDA | E7: 403 | F7: 36857 | I7: ACTIVA
A8: 7 | B8: ANTIOQUIA | C8: 811023570 | D8: L & D LOGISTICA DE DISTRIBUCION S.A. | E8: 422 | F8: 36864 | I8: ACTIVA
A9: 8 | B9: ANTIOQUIA | C9: 800122787 | D9: TRANSPORTES INOXIDABLES LTDA | E9: 429 | F9: 36873 | I9: ACTIVA
A10: 9 | B10: ANTIOQUIA | C10: 800094934 | D10: TRANSPORTADORA SURAMERICANA DE CARGA S.A. | E10: 21 | F10: 36899 | I10: ACTIVA
A11: 10 | B11: ANTIOQUIA | C11: 800231674 | D11: TRANSPORTADOR ALEF SAS | E11: 28 | F11: 36917 | I11: ACTIVA
A12: 11 | B12: ANTIOQUIA | C12: 890917639 | D12: TRANSPORTE DE MAQUINARIA LTDA | E12: 42 | F12: 36941 | I12: ACTIVA
A13: 12 | B13: ANTIOQUIA | C13: 800246302 | D13: TANQUES Y CAMIONES S.A.S | E13: 53 | F13: 36945 | I13: ACTIVA
... A513: 512 | B513: ANTIOQUIA | C513: 901819287 | D513: H+G LOGISTICA S.A.S. | E513: 20243050062895 | F513: 45646 | I513: ACTIVA
B514: ANTIOQUIA | C514: 900301490 | D514: CARRETERAS Y CANTERAS ANDINAS S.A.S | E514: 20253040016385 | F514: 45779 | I514: ACTIVA
B515: ANTIOQUIA | C515: 900999079 | D515: TRANSUIZA S.A.S | E515: 20253040016395 | F515: 45779 | I515: ACTIVA
A516: 513 | B516: ATLANTICO | C516: 802009926 | D516: TRANSQUIROGA LTDA. | E516: 45 | F516: 36347 | I516: ACTIVA
A517: 514 | B517: ATLANTICO | C517: 802004552 | D517: COMPAÑIA DE TRANSPORTE ESPECIAL DE LA COSTA CARIBE LTDA. | E517: 46 | F517: 36350 | I517: ACTIVA
A518: 515 | B518: ATLANTICO | C518: 802004356 | D518: GRANANDINA T. C. & CIA. LTDA. | E518: 55 | F518: 36377 | I518: ACTIVA
A519: 516 | B519: ATLANTICO | C519: 800070056 | D519: TRANSPORTES INTERTANQUES LTDA. | E519: 77 | F519: 36423 | I519: ACTIVA
A520: 517 | B520: ATLANTICO | C520: 890105310 | D520: TRANSPORTADORA DEL ATLANTICO LTDA. | E520: 103 | F520: 36475 | I520: ACTIVA
A521: 518 | B521: ATLANTICO | C521: 802002141 | D521: TRANSPORTO Y COMPAÑIA LTDA | E521: 21 | F521: 36577 | I521: ACTIVA
A522: 519 | B522: ATLANTICO | C522: 800054063 | D522: TRANSCOMERCIAL S.A.S | E522: 20 | F522: 36943 | I522: ACTIVA
A523: 520 | B523: ATLANTICO | C523: 800082024 | D523: ASOCIACION INTERNACIONAL DE CARGA LTDA. | E523: 4 | F523: 36943 | I523: ACTIVA
A524: 521 | B524: ATLANTICO | C524: 800113506 | D524: TRANSPORTES VERPER LTDA. | E524: 5 | F524: 36943 | I524: ACTIVA
A525: 522 | B525: ATLANTICO | C525: 800200080 | D525: TRANSPORTES COMANDER LTDA. | E525: 75 | F525: 36955 | I525: ACTIVA
A526: 523 | B526: ATLANTICO | C526: 800150150 | D526: TRANSPORTES SAPASA LTDA | E526: 147 | F526: 36991 | I526: ACTIVA
A527: 524 | B527: ATLANTICO | C527: 800137059 | D527: TRANSPORTE ZAMUDIO S.A.S. | E527: 66 | F527: 36992 | I527: ACTIVA
... A1141: 1138 | B1141: BOYACA | C1141: 826001705 | D1141: COOPERATIVA DE TRANSPORTADORES DEL ORIENTE COLOMBIANO | E1141: 90 | F1141: 36586 | I1141: ACTIVA
A1142: 1139 | B1142: BOYACA | C1142: 844000205 | D1142: TECNITRANSPORTES SOCIEDAD POR ACCIONES SIMPLIFICADA | E1142: 1 | F1142: 36627 | G1142: 91 | H1142: 42295 | I1142: ACTIVA
A1143: 1140 | B1143: BOYACA | C1143: 826001502 | D1143: COOPERATIVA DE TRANSPORTES DE NOBSA | E1143: 4 | F1143: 36642 | I1143: ACTIVA
A1144: 1141 | B1144: BOYACA | C1144: 800213811 | D1144: COOPERATIVA DE TRANSPORTES Y SERVICIOS DE CASANARE LTDA | E1144: 6 | F1144: 36658 | I1144: ACTIVA
A1145: 1142 | B1145: BOYACA | C1145: 826000851 | D1145: COOPERATIVA MULTIACTIVA DE TRANSPORTE DE CARGA RUTA DE LOS LIBERTADORES | E1145: 25 | F1145: 36766 | I1145: ACTIVA
A1146: 1143 | B1146: BOYACA | C1146: 844001863 | D1146: TRANSPORTES Y SERVICIOS G.C.C. LTDA | E1146: 119 | F1146: 36819 | I1146: ACTIVA
A1147: 1144 | B1147: BOYACA | C1147: 826001735 | D1147: COMPAÑIA DE INVERSIONES Y TRANSPORTES MARTHA S.A. | E1147: 1118 | F1147: 36819 | I1147: ACTIVA
A1148: 1145 | B1148: BOYACA | C1148: 800178864 | D1148: SERVICIOS Y TRANSPORTES CAMARGO HERNANDEZ MONTAÑA LTDA. | E1148: 223 | F1148: 36840 | I1148: ACTIVA
A1149: 1146 | B1149: BOYACA | C1149: 800178864 | D1149: ROAD CARGO S.A.S. | E1149: 223 | F1149: 36840 | I1149: ACTIVA
A1150: 1147 | B1150: BOYACA | C1150: 800171328 | D1150: SERVICUSIANA LIMITADA | E1150: 224 | F1150: 36854 | I1150: ACTIVA
A1151: 1148 | B1151: BOYACA | C1151: 800244321 | D1151: COOPERATIVA MULTIACTIVA DE TRANSPORTADORES DE TAURAMENA LTDA. | E1151: 293 | F1151: 36878 | I1151: ACTIVA
A1152: 1149 | B1152: BOYACA | C1152: 891800208 | D1152: ORGANIZACION COOPERATIVA DE TRANSPORTADORES ALIANZA CONTINENTAL O.C. | E1152: 17 | F1152: 36937 | I1152: ACTIVA
A1153: 1150 | B1153: BOYACA | C1153: 844002349 | D1153: DISTRIBUIDORES TRANSPORTADORES DEL LLANO SAS | E1153: 21 | F1153: 36948 | I1153: ACTIVA
A1154: 1151 | B1154: BOYACA | C1154: 826001705 | D1154: COOPERATIVA DE TRANSPORTADORES DEL ORIENTE COLOMBIANO | E1154: 90 | F1154: 36951 | I1154: ACTIVA
... A1161: 1158 | B1161: BOYACA | C1161: 891857894 | D1161: SOCIEDAD TRANSPORTADORA DE DUITAMA S.A.S. | E1161: 227 | F1161: 37084 | I1161: ACTIVA
A1162: 1159 | B1162: BOYACA | C1162: 820000086 | D1162: LUBRICANTES Y TRANSPORTES S.A.S. (ANTES: LUBRICANTES Y TRANSPORTES S. A.) | E1162: 235 | F1162: 37095 | G1162: 20253040003345 | H1162: 45695 | I1162: ACTIVA | J1162: CAMBIO DE TIPO SOCIETARIO
A1163: 1160 | B1163: BOYACA | C1163: 800168408 | D1163: COOPERATIVA DE TRANSPORTADORES UNIDOS DE BOYACA | E1163: 254 | F1163: 37124 | I1163: ACTIVA
A1164: 1161 | B1164: BOYACA | C1164: 832000591 | D1164: SERVICIOS Y TRANSPORTES LLANOVIAL SAS | E1164: 334 | F1164: 37183 | G1164: 15 | H1164: 42459 | I1164: ACTIVA
A1165: 1162 | B1165: BOYACA | C1165: 844002912 | D1165: SERVICIOS ESPECIALES EXPRESO DEL CUSIANA | E1165: 343 | F1165: 37202 | I1165: ACTIVA
A1166: 1163 | B1166: BOYACA | C1166: 844002514 | D1166: SERVICIOS Y TRANSPORTES DE AGUAZUL CASANARE LTDA. | E1166: 354 | F1166: 37204 | I1166: ACTIVA
A1167: 1164 | B1167: BOYACA | C1167: 844002514 | D1167: SERTRAC INGENIERIA S.A.S | E1167: 354 | F1167: 37204 | I1167: ACTIVA
A1168: 1165 | B1168: BOYACA | C1168: 844001363 | D1168: COOPERATIVA MULTIACTIVA DE TRANSPORTES Y SERVICIOS INTEGRADOS DEL CASAN | E1168: 357 | F1168: 37210 | I1168: ACTIVA
A1169: 1166 | B1169: BOYACA | C1169: 826002626 | D1169: SOCIEDAD GRAN TRANSPORTADORA B.N. LTDA. | E1169: 365 | F1169: 37217 | I1169: ACTIVA
A1170: 1167 | B1170: BOYACA | C1170: 800209179 | D1170: COLOMBIANA DE ENCOMIENDAS S.A. | E1170: 386 | F1170: 37235 | I1170: ACTIVA
A1171: 1168 | B1171: BOYACA | C1171: 800152509 | D1171: COOPERATIVA MULTIACTIVA DE TRANSPORTES Y SERVICIOS LTDA. | E1171: 427 | F1171: 37245 | I1171: ACTIVA
A1172: 1169 | B1172: BOYACA | C1172: 891857878 | D1172: TRANSPORTADORA BOYACENSE S.A. | E1172: 436 | F1172: 37246 | I1172: ACTIVA
A1173: 1170 | B1173: BOYACA | C1173: 826002513 | D1173: CARGANDO S. A. | E1173: 169 | F1173: 37365 | I1173: ACTIVA
A1174: 1171 | B1174: BOYACA | C1174: 826002563 | D1174: COOPERATIVA DE TRANSPORTES LOS LIBERTADORES DE COLOMBIA LTDA. | E1174: 194 | F1174: 37383 | I1174: ACTIVA
A1175: 1172 | B1175: BOYACA | C1175: 891800432 | D1175: COOPERATIVA DE TRANSPORTADORES DEL VALLE DE SAMACA O.C. | E1175: 197 | F1175: 37385 | I1175: ACTIVA
A1176: 1173 | B1176: BOYACA | C1176: 891855332 | D1176: COOPERATIVA TRANSPORTADORA DE CASANARE LTDA. | E1176: 196 | F1176: 37385 | I1176: ACTIVA
... A1191: 1188 | B1191: BOYACA | C1191: 800248052 | D1191: COOPERATIVA DE TRANSPORTADORES CUPIAGA | E1191: 550 | F1191: 37858 | I1191: ACTIVA
A1192: 1189 | B1192: BOYACA | C1192: 800160895 | D1192: LLANO MOTOR S.A. | E1192: 561 | F1192: 37872 | G1192: 20253040003595 | H1192: 45698 | I1192: ACTIVA | J1192: ACTUALIZA CARACTERÍSTICAS
A1193: 1190 | B1193: BOYACA | C1193: 891801450 | D1193: TRANSPORTES LOS MUISCAS S.A. | E1193: 636 | F1193: 37879 | I1193: ACTIVA
A1194: 1191 | B1194: BOYACA | C1194: 826003757 | D1194: ORGANIZACION INTERAMERICANA DE TRANSPORTES S. EN C.S. | E1194: 35 | F1194: 38096 | I1194: ACTIVA
A1195: 1192 | B1195: BOYACA | C1195: 826003942 | D1195: IMEGO CARGA SAS | E1195: 229 | F1195: 38223 | I1195: ACTIVA
A1196: 1193 | B1196: BOYACA | C1196: 844003380 | D1196: TRANSPORTADORES UNIDOS LTDA. | E1196: 295 | F1196: 38287 | I1196: ACTIVA
A1197: 1194 | B1197: BOYACA | C1197: 830064790 | D1197: INVERSIONES CASTAÑEDA CELY LTDA. | E1197: 149 | F1197: 38569 | I1197: ACTIVA
A1198: 1195 | B1198: BOYACA | C1198: 826000404 | D1198: COMERCIALIZADORA DE COMBUSTIBLES Y TRANSPORTES LTDA. | E1198: 209 | F1198: 38608 | I1198: ACTIVA
A1199: 1196 | B1199: BOYACA | C1199: 844005094 | D1199: CONSTRUCCIONES DE INGENIERIA Y SERVICIOS DE ARQUITECTURA SAS | E1199: 313 | F1199: 38705 | I1199: ACTIVA
A1200: 1197 | B1200: BOYACA | C1200: 826002101 | D1200: SERVICIOS Y PRODUCTOS LTDA | E1200: 140 | F1200: 38797 | I1200: ACTIVA
A1201: 1198 | B1201: BOYACA | C1201: 900064969 | D1201: CAMARGO PEREZ TRANSPORTADORES LTDA | E1201: 188 | F1201: 38873 | I1201: ACTIVA
A1202: 1199 | B1202: BOYACA | C1202: 900068145 | D1202: ORGANIZACION LOGISTICA TRANSPORTADORA S.A. | E1202: 203 | F1202: 38891 | I1202: ACTIVA
A1203: 1200 | B1203: BOYACA | C1203: 900078730 | D1203: TRANSCHIQUINQUIRA S.A. | E1203: 202 | F1203: 38891 | I1203: ACTIVA
A1204: 1201 | B1204: BOYACA | C1204: 844000827 | D1204: COOPERATIVA MULTIACTIVA DE TRABAJADORES EN EQUIPO LTDA | E1204: 290 | F1204: 39007 | I1204: ACTIVA
... A1234: 1231 | B1234: BOYACA | C1234: 900145350 | D1234: TANQUES Y TRANSPORTES DEL CASANARE LTDA. | E1234: 56 | F1234: 40080 | I1234: ACTIVA
A1235: 1232 | B1235: BOYACA | C1235: 900231855 | D1235: ENLACE DE TRANSPORTES Y SERVICIOS LTDA | E1235: 28 | F1235: 40094 | G1235: 33 | H1235: 42528 | I1235: ACTIVA
A1236: 1233 | B1236: BOYACA | C1236: 800081581 | D1236: TRANSPORTES ROZO LTDA. | E1236: 74 | F1236: 40144 | I1236: ACTIVA
A1237: 1234 | B1237: BOYACA | C1237: 844003489 | D1237: SERVICIOS Y CONSTRUCCIONES DEL ORIENTE LTDA. | E1237: 77 | F1237: 40163 | I1237: ACTIVA
A1238: 1235 | B1238: BOYACA | C1238: 900054431 | D1238: AGREGADOS TRANSCOLOMBIA LTDA. | E1238: 1 | F1238: 40185 | I1238: ACTIVA
A1239: 1236 | B1239: BOYACA | C1239: 900299342 | D1239: REGIOMONTUNA DE SERVICIOS LTDA. | E1239: 20 | F1239: 40329 | I1239: ACTIVA
A1240: 1237 | B1240: BOYACA | C1240: 900342431 | D1240: SERVICIOS INTEGRALES PALENQUERA S.A.S. | E1240: 57 | F1240: 40519 | I1240: ACTIVA
A1241: 1238 | B1241: BOYACA | C1241: 900364353 | D1241: TRANSPORTES MULTICARGA S.A.S. | E1241: 58 | F1241: 40519 | I1241: ACTIVA
A1242: 1239 | B1242: BOYACA | C1242: 900352248 | D1242: TRANSPORTES MORE CARGO SOCIEDAD POR ACCIONES SIMPLIFICADA | E1242: 65 | F1242: 40542 | I1242: ACTIVA
A1243: 1240 | B1243: BOYACA | C1243: 826003958 | D1243: SERVICIOS ESPECIALES ARCOIRIS LTDA. | E1243: 1 | F1243: 40546 | I1243: ACTIVA
A1244: 1241 | B1244: BOYACA | C1244: 900389337 | D1244: TRANSPORTES Y SERVICIOS NELSON SOCIEDAD POR ACCIONES SIMPLIFICADA | E1244: 3 | F1244: 40546 | I1244: ACTIVA
A1245: 1242 | B1245: BOYACA | C1245: 900385244 | D1245: TRAESCOL SAS | E1245: 5 | F1245: 40582 | G1245: 81 | H1245: 41527 | I1245: ACTIVA
A1246: 1243 | B1246: BOYACA | C1246: 900385244 | D1246: TRANSPORTES ESPECIALES DE COLOMBIA S.A.S. (TRAESCOL SAS) | E1246: 5 | F1246: 40582 | I1246: ACTIVA
A1247: 1244 | B1247: BOYACA | C1247: 844001084 | D1247: DISTRIBUCIONES ARIPORO LTDA. | E1247: 16 | F1247: 40603 | I1247: ACTIVA
A1248: 1245 | B1248: BOYACA | C1248: 900386213 | D1248: DISTRIBUIDOR Y TRANSPORTE DE CARGA S.A.S. | E1248: 17 | F1248: 40603 | I1248: ACTIVA
A1249: 1246 | B1249: BOYACA | C1249: 900400707 | D1249: MI CARGA S.A.S. | E1249: 27 | F1249: 40633 | I1249: ACTIVA
A1250: 1247 | B1250: BOYACA | C1250: 900415958 | D1250: GLOBAL SUPPORT & SERVICE S.A.S. | E1250: 40 | F1250: 40666 | I1250: ACTIVA
A1251: 1248 | B1251: BOYACA | C1251: 900318604 | D1251: TRANSPORTES Y SERVICIOS NACIONALES S.A.S. | E1251: 51 | F1251: 40715 | I1251: ACTIVA
A1252: 1249 | B1252: BOYACA | C1252: 900392705 | D1252: TRANSPORTE LOPECARGA S.A.S. | E1252: 66 | F1252: 40759 | I1252: ACTIVA
A1253: 1250 | B1253: BOYACA | C1253: 900445499 | D1253: AGROLOGISTICA ESPECIALIZADA SAS | E1253: 65 | F1253: 40759 | G1253: 115 | H1253: 41621 | I1253: ACTIVA
A1254: 1251 | B1254: BOYACA | C1254: 900393484 | D1254: SERVITRANSPORTES DE COLOMBIA S.A.S | E1254: 60 | F1254: 40764 | G1254: 34 | H1254: 40653 | I1254: ACTIVA
A1255: 1252 | B1255: BOYACA | C1255: 900334648 | D1255: SERVICIOS TRANSMANARE S.A.S. | E1255: 69 | F1255: 40779 | I1255: ACTIVA
A1256: 1253 | B1256: BOYACA | C1256: 900193101 | D1256: COMPAÑIA PRESTADORA DE SERVICIOS SAS. | E1256: 71 | F1256: 40788 | I1256: ACTIVA
A1257: 1254 | B1257: BOYACA | C1257: 900436922 | D1257: TRANSPORTE DE PETROLEO Y CARGA S.A.S. | E1257: 87 | F1257: 40823 | I1257: ACTIVA
A1258: 1255 | B1258: BOYACA | C1258: 900384085 | D1258: SERVICIOS MAQUITRANS S.A.S. | E1258: 92 | F1258: 40862 | I1258: ACTIVA
A1259: 1256 | B1259: BOYACA | C1259: 900471478 | D1259: ESTRATEGIA Y SERVICIO COLOMBIANO DE TRANSPORTE S.A.S. | E1259: 7 | F1259: 40946 | G1259: 17 | H1259: 41344 | I1259: ACTIVA
A1260: 1257 | B1260: BOYACA | C1260: 900475822 | D1260: ENVIOS & CARGA INTERNACIONAL | E1260: 12 | F1260: 40962 | G1260: 10 | H1260: 41338 | I1260: ACTIVA
A1261: 1258 | B1261: BOYACA | C1261: 900498442 | D1261: TANQUES Y SERVICIOS DEL CASANARE S.A.S. | E1261: 21 | F1261: 40977 | I1261: ACTIVA
...

Sheet IPS
A1: tienNombre | B1: codigo | C1: sigla | D1: nombre | E1: gerente | F1: depaNombre | G1: muniNombre | H1: direccion | I1: telefono | J1: email | K1: url | L1: url_red
A2: IPS Privadas | B2: 1100100032 | D2: COOPERATIVA PARA LA SALUD ORAL ORALCOOP | F2: BogotᬠD.C. | G2: BogotᬠD.C | H2: CARRERA 64 100-55 | I2: 5330539-3134241468 | J2: oralcoop@oralcoop.com
A3: IPS Privadas | B3: 110010003201 | D3: COOPERATIVA PARA LA SALUD ORAL ORALCOOP | E3: PEDRO ANDRES MANTILLA DURAN | F3: BogotᬠD.C. | G3: BogotᬠD.C | H3: KR 64 # 100 55 | I3: 5330539-3134241468 | J3: oralcoop@oralcoop.com
A4: IPS Privadas | B4: 1100100129 | D4: ASOCIACION CENTRO DE EDUCACION ESPECIAL REHABILITACION Y CAPACITACION RENACER | E4: JOSE ERNESTO CHAPARRO SARMIENTO | F4: BogotᬠD.C. | G4: BogotᬠD.C | H4: CL 33 # 19 36 | I4: 4807256 | J4: insrenacer@hotmail.com
A5: IPS Privadas | B5: 110010012901 | D5: ASOCIACION CENTRO DE EDUCACION ESPECIAL REHABILITACION Y CAPACITACION RENACER | E5: JOSE ERNESTO CHAPARRO SARMIENTO | F5: BogotᬠD.C. | G5: BogotᬠD.C | H5: CL 33 # 19 36 | I5: 4807256 | J5: insrenacer@hotmail.com
A6: IPS Privadas | B6: 110010012902 | D6: ASOCIACION CENTRO DE EDUCACION ESPECIAL REHABILITACION Y CAPACITACION RENACER | E6: JOSE ERNESTO CHAPARRO SARMIENTO | F6: BogotᬠD.C. | G6: BogotᬠD.C | H6: CL 33 # 19 25 | I6: 6055323 | J6: insrenacer@hotmail.com
A7: IPS Privadas | B7: 1100100130 | D7: INVERSIONES DAMA SALUD SAS | E7: JENNY ALEXANDRA ARIAS MARTINEZ | F7: BogotᬠD.C. | G7: BogotᬠD.C | H7: KR 13 # 57-12 - Barrio:CHAPINERO | I7: 3115892080 | J7: coordinadorhabilitacion@sonria.com.co | K7: WWW.SONRIA.COM.CO
A8: IPS Privadas | B8: 110010013002 | D8: SONRIA DAMA SALUD SEDE RESTREPO | E8: LUISA FERNANDA AGUDELO ALEMAN | F8: BogotᬠD.C. | G8: BogotᬠD.C | H8: DIAGONAL 19 SUR No 20 -39 | I8: 3665265 | J8: coordinadorhabilitacion@sonria.com.co
A9: IPS Privadas | B9: 110010013003 | D9: SONRIA DAMA SALUD SEDE QUIRIGUA | E9: MONICA MAYERLY ARIZA HERREя | F9: BogotᬠD.C. | G9: BogotᬠD.C | H9: TV 94A # 80A 91 | I9: 4425296 | J9: coordinadorhabilitacion@sonria.com.co
A10: IPS Privadas | B10: 110010013004 | D10: SONRIA DAMA SALUD SEDE GALERIAS | E10: LUISA AGUDELO ALEMAN | F10: BogotᬠD.C. | G10: BogotᬠD.C | H10: AC 53 N 25 - 03 LC | I10: 3580424 | J10: coordinadorhabilitacion@sonria.com.co
A11: IPS Privadas | B11: 110010013005 | D11: SONRIA DAMA SALUD SEDE KENNEDY | E11: YURI ADRIANA ESCUDERO HERRN | F11: BogotᬠD.C. | G11: BogotᬠD.C | H11: AK 80 No 55 - 37 SUR LC | I11: 7824756 | J11: coordinadorhabilitacion@sonria.com.co
A12: IPS Privadas | B12: 110010013007 | D12: SONRIA DAMA SALUD SEDE AV 68 | E12: MARIA XIMENA SCARPETTA ROZO | F12: BogotᬠD.C. | G12: BogotᬠD.C | H12: AC 72 No. 76 - 76 | I12: 2230775 | J12: coordinadorhabilitacion@sonria.com.co
A13: IPS Privadas | B13: 110010013008 | D13: SONRIA DAMA SALUD SEDE FONTIBON | E13: ANA MARIA CAMARGO NAVARRETE | F13: BogotᬠD.C. | G13: BogotᬠD.C | H13: CRA 99 # 18 04 | I13: 2984202 | J13: coordinadorhabilitacion@sonria.com.co
A14: IPS Privadas | B14: 110010013009 | D14: SONRIA DAMA SALUD SEDE SUBA | E14: IRMA CONSTANZA PIхROS CARDENAS | F14: BogotᬠD.C. | G14: BogotᬠD.C | H14: CRA 92 # 147 68 LOCAL 22 | I14: 6819121 | J14: coordinadorhabilitacion@sonria.com.co
A15: IPS Privadas | B15: 110010013010 | D15: SONRIA DAMA SALUD SEDE TECHO | E15: YURI ADRIANA ESCUDERO HERRN | F15: BogotᬠD.C. | G15: BogotᬠD.C | H15: CARRERA 78 B NO 38 C 23 SUR | I15: 3580454 | J15: coordinadorhabilitacion@sonria.com.co
A16: IPS Privadas | B16: 110010013011 | D16: SONRIA DAMA SALUD SEDE TUNAL | E16: JACOBO ENRIQUE DEL RIO CEDEя | F16: BogotᬠD.C. | G16: BogotᬠD.C | H16: CR 25 # 48 - 09 SUR | I16: 2049827 | J16: coordinadorhabilitacion@sonria.com.co
A17: IPS Privadas | B17: 110010013013 | D17: SONRIA DAMA SALUD SEDE C.C HAYUELOS | E17: STEPHANY ATEHORTUA SANCHEZ | F17: BogotᬠD.C. | G17: BogotᬠD.C | H17: CALLE 20 # 82-52 LOCAL 1-66C/1-66B PISO 1 HAYUELOS CENTRO COMERCIAL Y EMPRESARIAL | I17: 4462808 | J17: coordinadorhabilitacion@sonria.com.co
A18: IPS Privadas | B18: 110010013015 | D18: SONRIA DAMA SALUD SEDE C.C GRAN PLAZA EL ENSUEя | E18: ANGELA ROCIO MORENO ANDRADE | F18: BogotᬠD.C. | G18: BogotᬠD.C | H18: CALLE 59 S # 51 - 21 LC 145 | I18: 3580432 | J18: coordinadorhabilitacion@sonria.com.co
A19: IPS Privadas | B19: 110010013016 | D19: SONRIA DAMA SALUD SEDE VENECIA | E19: CINDY PAOLA ALVARADO VIDES | F19: BogotᬠD.C. | G19: BogotᬠD.C | H19: AUTOP. SUR N 54A-25 | I19: 7416100 | J19: coordinadorhabilitacion@sonria.com.co
... A38: IPS Privadas | B38: 110010022401 | D38: ETICA ORAL LIMITADA | E38: HUMBERTO VILA VALERA | F38: BogotᬠD.C. | G38: BogotᬠD.C | H38: CL 127 No 19A - 44 /62 P2 CONS 202-203 ACOMEDICA 2 | I38: 6025050 | J38: servietica@yahoo.com
A39: IPS Privadas | B39: 1100100356 | D39: BIONUCLEAR S.A.S | E39: MERCEDES CHINOME | F39: BogotᬠD.C. | G39: BogotᬠD.C | H39: AK 45 # 106 30 OFICINA 204, CONSULTORIO 201 Y 209 | I39: 3044350519 - 3008589820 | J39: bionuclearsas@gmail.com
A40: IPS Privadas | B40: 110010035601 | D40: BIONUCLEAR | E40: ARIEL MORENO CACERES | F40: BogotᬠD.C. | G40: BogotᬠD.C | H40: AK 45 # 106 30PI 2 | I40: 3044350519 - 3008589820 | J40: bionuclearsas@gmail.com
A41: IPS Privadas | B41: 1100100396 | D41: CLINICA RETORNAR SAS | E41: MARAI DEL PILAR JAIME IZQUIERDO | F41: BogotᬠD.C. | G41: BogotᬠD.C | H41: AK 20 87 33 | I41: 7957100 | J41: obarrera@clinicaretornar.com
A42: IPS Privadas | B42: 110010039601 | D42: CLINICA RETORNAR | E42: MARIA DEL PILAR JAIME IZQUIERDO | F42: BogotᬠD.C. | G42: BogotᬠD.C | H42: AK 20 87 33 | I42: 6015807939 | J42: obarrera@clinicaretornar.com
A43: IPS Privadas | B43: 110010039602 | D43: CLINICA RETORNAR SAS | E43: MARIA DEL PILAR JAIME IZQUIERDO | F43: BogotᬠD.C. | G43: BogotᬠD.C | H43: CR 24 NO. 84 46 | I43: 7957100 ext | J43: obarrera@clinicaretornar.com
A44: IPS Privadas | B44: 1100100483 | D44: SALUD INTEGRAL EL LAGO LTDA | E44: FAJARDO DIAZ FRANCISCO ANTONIO | F44: BogotᬠD.C. | G44: BogotᬠD.C | H44: CL 79 # 18 34 CS 506 | I44: 8056234 | J44: info@saludintegralellago.co
A45: IPS Privadas | B45: 110010048301 | D45: SALUD INTEGRAL EL LAGO LTDA | E45: MARCO ALBERTO FAJARDO DIAZ | F45: BogotᬠD.C. | G45: BogotᬠD.C | H45: CALLE 79 No. 18 - 34 C- 506 | I45: 8056234 | J45: info@saludintegralellago.co
A46: IPS Privadas | B46: 1100100518 | D46: OPTICA COLOMBIANA S.A.S | E46: MEJIA HENAO RODRIGO | F46: BogotᬠD.C. | G46: BogotᬠD.C | H46: CRA 12 N 82-02 LC 2-08 | I46: 2369824 | J46: contab@opticacolombiana.com
A47: IPS Privadas | B47: 110010051803 | D47: OPTICA COLOMBIANA S.A.S - NIZA | E47: Maria Alejandra Cuervo Mosquera | F47: BogotᬠD.C. | G47: BogotᬠD.C | H47: CARRERA 52 # 125A - 59 LC 1-62 | I47: 601 3264500 Ext 4123 | J47: niza@opticacolombiana.com
A48: IPS Privadas | B48: 110010051805 | D48: OPTICA COLOMBIANA S.A.S EXITO CALLE 80 | E48: Maria Alejandra Cuervo Mosquera | F48: BogotᬠD.C. | G48: BogotᬠD.C | H48: KR 59 A 79 - 30 LC L0124 | I48: 601 3264500 Ext 4109 | J48: calle80@opticacolombiana.com
A49: IPS Privadas | B49: 110010051810 | D49: OPTICA COLOMBIANA S.A.S CENTRO COMERCIAL ANDINO | E49: Maria Alejandra Cuervo Mosquera | F49: BogotᬠD.C. | G49: BogotᬠD.C | H49: CRA 12 N 82 - 02 LC 2-08 | I49: 601 3264500 Ext 4101 | J49: andino@opticacolombiana.com
A50: IPS Privadas | B50: 110010051811 | D50: OPTICA COLOMBIANA S.A.S - PALATINO | E50: Maria Alejandra Cuervo Mosquera | F50: BogotᬠD.C. | G50: BogotᬠD.C | H50: KR 7 # 139 07 LC 204 | I50: 601 3264500 Ext 4108 | J50: palatino@opticacolombiana.com
A51: IPS Privadas | B51: 110010051814 | D51: OPTICA COLOMBIANA S.A.S CENTRO COMERCIAL SANTAFE | E51: Maria Alejandra Cuervo Mosquera | F51: BogotᬠD.C. | G51: BogotᬠD.C | H51: CLL 185 # 45-03 LC 225 | I51: 601 3264500 Ext 4113 | J51: santafebogota@opticacolombiana.com
A52: IPS Privadas | B52: 110010051817 | D52: OPTICA COLOMBIANA S.A.S - GRAN ESTACION | E52: Maria Alejandra Cuervo Mosquera | F52: BogotᬠD.C. | G52: BogotᬠD.C | H52: AC 26 N 62 -47 LC 2-24 | I52: 601 3264500 Ext 4102 | J52: granestacion@opticacolombiana.com
A53: IPS Privadas | B53: 110010051818 | D53: OPTICA COLOMBIANA S.A.S - UNICENTRO BOGOTA | E53: Maria Alejandra Cuervo Mosquera | F53: BogotᬠD.C. | G53: BogotᬠD.C | H53: Avenida 15 No 123-30 LC 2-26 CS 1 | I53: 601 3264500 Ext 4118 | J53: unicentrobogota@opticacolombiana.com
A54: IPS Privadas | B54: 110010051819 | D54: OPTICA COLOMBIANA S.A.S CENTRO COMERCIAL SAN MARTIN | E54: Maria Alejandra Cuervo Mosquera | F54: BogotᬠD.C. | G54: BogotᬠD.C | H54: KR 7 # 32 - 12 LOCAL 121 | I54: 601 3264500 Ext 4116 | J54: sanmartin@opticacolombiana.com
A55: IPS Privadas | B55: 110010051823 | D55: OPTICA COLOMBIANA S.A.S - PARQUE LA COLINA | E55: Maria Alejandra Cuervo Mosquera | F55: BogotᬠD.C. | G55: BogotᬠD.C | H55: CR 58 D N 146-51 LOCAL 253 B | I55: 601 3264500 Ext 4125 | J55: parquecolina@opticacolombiana.com
A56: IPS Privadas | B56: 110010051824 | D56: OPTICA COLOMBIANA S.A.S - PLAZA CENTRAL | E56: Maria Alejandra Cuervo Mosquera | F56: BogotᬠD.C. | G56: BogotᬠD.C | H56: CR 65 N 11 - 50 CC. PLAZA CENTRAL ESPACIO 1-29 | I56: 601 3264500 Ext 4124 | J56: plazacentral@opticacolombiana.com
A57: IPS Privadas | B57: 1100100592 | D57: UNIDAD RADIOLOGICA DENTO CRANEO MAXILO FACIAL S.A. | E57: DACHIARDI REY ALBERTO | F57: BogotᬠD.C. | G57: BogotᬠD.C | H57: CL 125 No. 20 - 70 OF 204 | I57: 6012153469 - 3226313167 | J57: unidadradiologica125@gmail.com
A58: IPS Privadas | B58: 110010059201 | D58: UNIDAD RADIOLOGICA DENTO CRANEO MAXILO FACIAL | F58: BogotᬠD.C. | G58: BogotᬠD.C | H58: CL 125 No. 20 - 70 OF 204 | I58: 6016291124 - 3226313167 | J58: unidadradiologica125@gmail.com
A59: IPS Privadas | B59: 110010059204 | D59: UNIDAD RADIOLOGICA DENTO CRANEO MAXILO FACIAL | F59: BogotᬠD.C. | G59: BogotᬠD.C | H59: CL 77 No. 16 - 20 OF 507 - 509 / 511 | I59: 6016232761 - 3226313167 | J59: unidadradiologica125@gmail.com
A60: IPS Privadas | B60: 1100100616 | D60: CENTRO DE ENFERMEDADES DIGESTIVAS SAS | E60: PINEDA OVALLE LUIS FERNANDO | F60: BogotᬠD.C. | G60: BogotᬠD.C | H60: CL 97 # 23 37 LOCAL 104 | I60: 6427200 | J60: abonilla@gutmedica.com
A61: IPS Privadas | B61: 110010061601 | D61: GUTMEDICA ALMIRANTE | E61: ADRIANNA LUCIA BONILLA GARZON | F61: BogotᬠD.C. | G61: BogotᬠD.C | H61: CR 16 # 84A - 09 CS 311 | I61: 6427200 | J61: abonilla@gutmedica.com
A62: IPS Privadas | B62: 110010061602 | D62: GUTMEDICA DALI | E62: ADRIANNA LUCIA BONILLA GARZON | F62: BogotᬠD.C. | G62: BogotᬠD.C | H62: Cl 97 # 23-37 Cs 302, 303. 315-11,315-6,315-5, Areas 315,204 Y 201 | I62: 6427200 | J62: abonilla@gutmedica.com
A63: IPS Privadas | B63: 1100100661 | D63: LITOMEDICA S.A | E63: RUEDA SALAZAR MANUEL MARCELO | F63: BogotᬠD.C. | G63: BogotᬠD.C | H63: CRA 13 # 49-40 CONSULTORIO 620 Y 624 - 1 LITOMEDICA | I63: 7448024, 7448204, 3436600 | J63: litomedicacorrespondencia@gmail.com
A64: IPS Privadas | B64: 110010066101 | D64: LITOMEDICA S.A | E64: MANUEL MARCELO RUEDA SALAZAR | F64: BogotᬠD.C. | G64: BogotᬠD.C | H64: CRA 13 # 49-40 CONSULTORIO 620 Y 624 - 1 LITOMEDICA | I64: 7448024-7448204 - 3014606499 | J64: litomedicasa@yahoo.es
A65: IPS Privadas | B65: 110010066102 | D65: LITOMEDICA CENTRO MEDICO ALMIRANTE COLON | E65: MANUEL MARCELO RUEDA SALAZAR | F65: BogotᬠD.C. | G65: BogotᬠD.C | H65: Cr 16 N 84 A 09 Cs 611 | I65: (601)8056344 | J65: litomedicasa@yahoo.es
A66: IPS Privadas | B66: 110010066103 | D66: LITOMEDICA MARLY CALLE 50 | E66: MANUEL MARCELO RUEDA SALAZAR | F66: BogotᬠD.C. | G66: BogotᬠD.C | H66: CALLE 50 N 9-16 Local 2 TAC y Local 3 RMN | I66: 745 60 36, 600 87 03, 600 87 04. | J66: litomedicasa@yahoo.es
A67: IPS Privadas | B67: 110010066105 | D67: LITOMEDICA URODINAMIA | E67: MANUEL MARCELO RUEDA SALAZAR | F67: BogotᬠD.C. | G67: BogotᬠD.C | H67: CALLE 50 N 7 - 36 PISO 3 | I67: 7440052 | J67: litomedicasa@yahoo.es
A68: IPS Privadas | B68: 1100100670 | D68: FUNDACION PARA LA REHABILITACION DE ALCOHOLICOS Y ADICTOS-FUNDAR | E68: GUTIERREZ OSORIO JOSE GOETHE | F68: BogotᬠD.C. | G68: BogotᬠD.C | H68: CRA 16 # 36 22 | I68: 7324044 | J68: ffundar@ffundar.org
A69: IPS Privadas | B69: 110010067001 | D69: FUNDACION PARA LA REHABILITACION DE ALCOHOLICOS Y ADICTOS - FUNDAR | E69: EDGAR ANDRES BARRETO AGUDELO | F69: BogotᬠD.C. | G69: BogotᬠD.C | H69: KR 16 # 36 22 | I69: 7324044 | J69: ffundar@ffundar.org
A70: IPS Privadas | B70: 1100100732 | D70: OPTICA DR MENDEZ S A S | E70: MENDEZ ANGULO LUIS JORGE | F70: BogotᬠD.C. | G70: BogotᬠD.C | H70: KR 19 # 100 10 - Barrio:CHAPINERO | I70: 6358141 | J70: gerencia@opticadrmendez.com | K70: www.opticadrmendez.com
A71: IPS Privadas | B71: 110010073203 | D71: OPTICA DR MENDEZ SAS | E71: LUIS JORGE MENDEZ ANGULO | F71: BogotᬠD.C. | G71: BogotᬠD.C | H71: KR 7 # 115 60 LC B 112 - 160 | I71: 6121940 | J71: optimendez@yahoo.com
A72: IPS Privadas | B72: 110010073204 | D72: OPTICA DR MENDEZ SAS | E72: LUIS JORGE MENDEZ ANGULO | F72: BogotᬠD.C. | G72: BogotᬠD.C | H72: KR 19 # 100 10 | I72: 6358141 | J72: opticadrmendez@yahoo.es
A73: IPS Privadas | B73: 1100100733 | D73: CEUSA CENTRO DE ESPECIALISTAS EN UROLOGIA S A | E73: VARGAS CABRERA CARLOS ENRIQUE | F73: BogotᬠD.C. | G73: BogotᬠD.C | H73: CARRERA 16 NO. 84A - 09 OFICINA 419 | I73: 6217017- 3166929389 | J73: ceusa1@outlook.com
A74: IPS Privadas | B74: 110010073305 | D74: CEUSA CENTRO DE ESPECIALISTAS EN UROLOGIA S A | E74: Carlos Enrique Vargas Cabrera | F74: BogotᬠD.C. | G74: BogotᬠD.C | H74: CARRERA 16 A NO. 84 05 PISO 6 | I74: 6217017-3166929389 | J74: ceusa1@outlook.com
A75: IPS Privadas | B75: 1100100923 | D75: UNIDAD DERMATOLOGICA DE FOTOTERAPIA SAS | E75: HERNANDEZ DE CHALELA CECILIA | F75: BogotᬠD.C. | G75: BogotᬠD.C | H75: Transversal 55 98 A 66 Oficina 405 Centro Comercial Iserra 100 | I75: 4263111 | J75: gerencia@udf.com.co
A76: IPS Privadas | B76: 110010092301 | D76: UNIDAD DERMATOLOGICA DE FOTOTERAPIA SAS | E76: ANDREA LEON PILONIETA | F76: BogotᬠD.C. | G76: BogotᬠD.C | H76: Transversal 55 98 A 66 Oficina 405 Centro Comercial Iserra 100 | I76: 4263111 | J76: gerencia@udf.com.co
A77: IPS Privadas | B77: 110010092302 | D77: UNIDAD DERMATOLOGICA Y DE FOTOTERAPIA | E77: ANDREA LEON PILONIETA | F77: BogotᬠD.C. | G77: BogotᬠD.C | H77: AVENIDA AMERICAS No. 62-84 Local 2-19 | I77: 4263111 | J77: gerencia@udf.com.co
A78: IPS Privadas | B78: 1100100930 | D78: FUNDACION CENTRO DE INVESTIGACION E INFORMACION EN DEFICIENCIAS AUDITIVAS-""CINDA""" | E78: DI-COLLOREDO MELS PALAU PAOLA MARIA PIA TADEA | F78: BogotᬠD.C. | G78: BogotᬠD.C | H78: CALLE 35 No. 17-24 | I78: 2455509-2881801-3166243334-3174383710 | J78: administracion@fundacioncinda.org
A79: IPS Privadas | B79: 110010093001 | D79: FUNDACION CENTRO DE INVESTIGACION E INFORMACION EN DEFICIENCIAS AUDITIVAS-""CINDA""" | E79: PAOLA MARIA PIA TADEA DI COLLOREDO MELS PALAU | F79: BogotᬠD.C. | G79: BogotᬠD.C | H79: Calle 35 No.17-24 | I79: 2455509-2881801-3166243334-3174383710 | J79: administracion@fundacioncinda.org
A80: IPS Privadas | B80: 1100100997 | D80: ASOCIACION CENTRO DE ATENCION PARA NIяS CON TRASTORNOS SENSORIOMOTORES ""ACONIя""" | E80: ACEVEDO DE RONDEROS BEATRIZ EUGENIA | F80: BogotᬠD.C. | G80: BogotᬠD.C | H80: CALLE 127 B # 45-28 | I80: 6508473 | J80: administracion@aconino.org | K80: http://www.aconino.org/
A81: IPS Privadas | B81: 110010099701 | D81: ASOCIACION CENTRO DE ATENCION PARA NIяS CON TRASTORNOS SENSORIOMOTORES ""ACONIя""" | F81: BogotᬠD.C. | G81: BogotᬠD.C | H81: CALLE 127 B # 45-28 | I81: 6508473 | J81: administracion@aconino.org
A82: IPS Privadas | B82: 110010099702 | D82: ASOCIACION CENTRO DE ATENCION PARA NIяS CON TRASTORNOS SENSORIOMOTORES ""ACONIя" | E82: LUISA FERNANDA VARGAS GUTIERREZ | F82: BogotᬠD.C. | G82: BogotᬠD.C | H82: CL 6A No.71A-10 | I82: 2900521 | J82: administracion@aconino.org
A83: IPS Privadas | B83: 1100101010 | D83: INVERSIONES EN RECREACION DEPORTE Y SALUD S.A. Sigla: BODYTECH S.A. | E83: Raul Pineda | F83: BogotᬠD.C. | G83: BogotᬠD.C | H83: carrera 19 B # 83-11 | I83: 7442222- EXT 40257 CELULAR 3213046169 | J83: constanza.fonseca@bodytechcorp.com | K83: www.bodytech.com.co
A84: IPS Privadas | B84: 110010101001 | D84: IPS CENTRO MEDICO DEPORTIVO BODYTECH CHAPINERO | E84: JENNY ALEJANDRA PINZON BOHORQUEZ | F84: BogotᬠD.C. | G84: BogotᬠD.C | H84: CRA 7 # 63 25 | I84: 7442222 EXT 42104 | J84: chapinero@bodytechcorp.com
A85: IPS Privadas | B85: 110010101002 | D85: IPS CENTRO MEDICO DEPORTIVO BODYTECH CEDRITOS | E85: JULIANA MARTINEZ MORENO | F85: BogotᬠD.C. | G85: BogotᬠD.C | H85: Cl 147 # 7 - 52 Piso 2 CC Show Place | I85: 7442222 EXT 41300 | J85: cedritos@bodytechcorp.com
A86: IPS Privadas | B86: 110010101003 | D86: IPS CENTRO MEDICO DEPORTIVO BODYTECH COLINA | E86: GLORIA ALEXANDRA FANDIя MATUK | F86: BogotᬠD.C. | G86: BogotᬠD.C | H86: AC 138 # 58 -74 PISO 2 | I86: 7442222 EXT 41604 | J86: colina@bodytechcorp.com
A87: IPS Privadas | B87: 110010101004 | D87: IPS CENTRO MEDICO DEPORTIVO BODYTECH CHICO | E87: ERWIN ALEXANDER ROMERO VELANDIA | F87: BogotᬠD.C. | G87: BogotᬠD.C | H87: Av 19 # 102 - 31 Piso 3 Entrada 1 | I87: 7442222 EXT 41504 | J87: chico@bodytechcorp.com
A88: IPS Privadas | B88: 110010101005 | D88: IPS CENTRO MEDICO DEPORTIVO ATHLETIC SALITRE | E88: MIGUEL ANGEL PEс OLAVE | F88: BogotᬠD.C. | G88: BogotᬠD.C | H88: AV 68 # 23 45 | I88: 3017158114 | J88: salitre.gerente@athleticgym.com.co
A89: IPS Privadas | B89: 110010101006 | D89: IPS CENTRO MEDICO DEPORTIVO BODYTECH AUTOPISTA 135 | E89: YUHEIDYS JOHANNA CERVERA SIERRA | F89: BogotᬠD.C. | G89: BogotᬠD.C | H89: CALLE 134 A No 23-72 | I89: 7442222 EXT 41004 | J89: autopista135@bodytechcorp.com
A90: IPS Privadas | B90: 110010101007 | D90: IPS CENTRO MEDICO DEPORTIVO BODYTECH PASADENA | E90: CAMILO ANDRES CASTRO MANZO | F90: BogotᬠD.C. | G90: BogotᬠD.C | H90: KR 53- 102 A 77 LOCAL 201 | I90: 7442222 EXT 42300 | J90: pasadena@bodytechcorp.com
A91: IPS Privadas | B91: 110010101008 | D91: IPS CENTRO MEDICO DEPORTIVO BODYTECH CABRERA | E91: DIANA MILENA ARIAS PRADA | F91: BogotᬠD.C. | G91: BogotᬠD.C | H91: CL 85 # 7 13 | I91: 7442222 EXT 41204 | J91: cabrera@bodytechcorp.com
A92: IPS Privadas | B92: 110010101010 | D92: IPS CENTRO MEDICO DEPORTIVO BODYTECH TORRE CENTRAL | E92: KATHERINE RAMIREZ SUAREZ | F92: BogotᬠD.C. | G92: BogotᬠD.C | H92: Calle 26 No 68 C -61 LOCAL 116 | I92: 7442222 EXT 42800 | J92: torrecentral@bodytechcorp.com
A93: IPS Privadas | B93: 110010101011 | D93: IPS CENTRO MEDICO DEPORTIVO BODYTECH SULTANA | E93: NELSON GASPAR PENAGOS MENDEZ | F93: BogotᬠD.C. | G93: BogotᬠD.C | H93: Calle 12 Sur No. 31-33 | I93: 7442222 EXT 42700 | J93: sultana@bodytechcorp.com
A94: IPS Privadas | B94: 110010101012 | D94: IPS CENTRO MEDICO DEPORTIVO BODYTECH PABLO VI | E94: VIVIANA MARCELA NAVARRETE QUIROGA | F94: BogotᬠD.C. | G94: BogotᬠD.C | H94: Cra 52 Bis # 56 B 26 Piso 2 | I94: 7442222 EXT 42200 | J94: pablovi@bodytechcorp.com
A95: IPS Privadas | B95: 110010101013 | D95: IPS CENTRO MEDICO DEPORTIVO BODYTECH SUBA | E95: NATALY RINCON MORA | F95: BogotᬠD.C. | G95: BogotᬠD.C | H95: Av Cr 104 # 148 - 07 Loc 269 Cc Plaza Imperial | I95: 7442222 EXT 42600 | J95: suba@bodytechcorp.com
A96: IPS Privadas | B96: 110010101014 | D96: IPS CENTRO MEDICO DEPORTIVO BODYTECH PORTAL 80 | E96: JEIMY NATHALY RODRIGUEZ OSORIO | F96: BogotᬠD.C. | G96: BogotᬠD.C | H96: Tv 100 A # 80 A 20 Lc 30-01 Centro Comercial Portal 80 | I96: 7442222 EXT 42400 | J96: portal80@bodytechcorp.com
A97: IPS Privadas | B97: 110010101016 | D97: IPS CENTRO MEDICO DEPORTIVO BODYTECH AUTOPISTA 170 | E97: AURA DEL ROSARIO MORENO MORA | F97: BogotᬠD.C. | G97: BogotᬠD.C | H97: Auto Norte # 167 - 10 | I97: 3142254617 | J97: autopista170@bodytechcorp.com
A98: IPS Privadas | B98: 110010101017 | D98: IPS CENTRO MEDICO DEPORTIVO BODYTECH KENNEDY | E98: DIANA MILENA OSORIO VARGAS | F98: BogotᬠD.C. | G98: BogotᬠD.C | H98: Transversal 78J No. 41F-05 Sur | I98: 7442222 EXT 41904 | J98: kennedy@bodytechcorp.com
A99: IPS Privadas | B99: 110010101018 | D99: IPS CENTRO MEDICO DEPORTIVO BODYTECH NORMANDIA | E99: PAOLA ANGELINA CASTAхDA CARDENAS | F99: BogotᬠD.C. | G99: BogotᬠD.C | H99: AVENIDA BOYACA No. 49-29 PISO 2 | I99: 7442222 EXT 35209 | J99: normandia@bodytechcorp.com
A100: IPS Privadas | B100: 110010101019 | D100: IPS CENTRO MEDICO DEPORTIVO BODYTECH HAYUELOS | E100: CAROLINA CACERES ESPITIA | F100: BogotᬠD.C. | G100: BogotᬠD.C | H100: Calle 20 No. 82-52 Local 4-59 | I100: 7442222 EXT 41800 | J100: hayuelos@bodytechcorp.com
A101: IPS Privadas | B101: 110010101021 | D101: IPS CENTRO MEDICO DEPORTIVO BODYTECH FLORESTA | E101: SHERYL NICKOLL ALVAREZ ROJAS | F101: BogotᬠD.C. | G101: BogotᬠD.C | H101: Avenida Carrera 68 #90 88 Nivel 0 | I101: 3102185548 | J101: floresta@bodytechcorp.com
A102: IPS Privadas | B102: 110010101023 | D102: IPS CENTRO MEDICO DEPORTIVO BODYTECH CENTRO MAYOR | E102: LORENA DEL PILAR URZOLA GOMEZ | F102: BogotᬠD.C. | G102: BogotᬠD.C | H102: CALLE 38 A SUR NO 34 D- 50 LOC 1-145 | I102: 7442222 EXT 35800 | J102: centromayor@bodytechcorp.com
A103: IPS Privadas | B103: 110010101026 | D103: IPS CENTRO MEDICO DEPORTIVO BODYTECH TITAN PLAZA | E103: MIGUEL ANGEL MURCIA PINILLA | F103: BogotᬠD.C. | G103: BogotᬠD.C | H103: CR 72 80-94 LC SE 4-27 | I103: 7442222 EXT 45104 | J103: titanplaza@bodytechcorp.com
A104: IPS Privadas | B104: 110010101028 | D104: IPS CENTRO MEDICO DEPORTIVO BODYTECH CARRERA 11 | E104: JENNY ANGELICA ZALDUA ORJUELA | F104: BogotᬠD.C. | G104: BogotᬠD.C | H104: CL 96 - 10-38 | I104: 7442222 EXT 45304 | J104: carrera11@bodytechcorp.com
A105: IPS Privadas | B105: 110010101029 | D105: IPS CENTRO MEDICO DEPORTIVO BODYTECH BULEVAR | E105: MARIA LILIANA BOLIVAR BOLIVAR | F105: BogotᬠD.C. | G105: BogotᬠD.C | H105: CR 58 127-29 LC 181 B | I105: 3102830824-3102677727 | J105: bulevar@bodytechcorp.com
A106: IPS Privadas | B106: 110010101030 | D106: IPS CENTRO MEDICO DEPORTIVO BODYTECH PLAZA CENTRAL | E106: NIDYA CONSUELO LOPEZ CABALLERO | F106: BogotᬠD.C. | G106: BogotᬠD.C | H106: CC PLAZA CENTRAL CRA 65 11-48 L 3-28 | I106: 7422639/3102839346 | J106: plazacentral@bodytechcorp.com
A107: IPS Privadas | B107: 110010101031 | D107: IPS CENTRO MEDICO DEPORTIVO BODYTECH DIVERPLAZA | E107: DARIO URUEс MACHADO | F107: BogotᬠD.C. | G107: BogotᬠD.C | H107: TV 99 # 70 A 89 | I107: 7422668 - 3103486324 | J107: diverplaza@bodytechcorp.com
A108: IPS Privadas | B108: 110010101032 | D108: IPS CENTRO MEDICO DEPORTIVO BODYTECH GRAN ESTACION | E108: JAVIER MATEO ZAMBRANO ROCHA | F108: BogotᬠD.C. | G108: BogotᬠD.C | H108: AC 26 No 62-47 P 4 | I108: 3014966267 | J108: granestacion@bodytechcorp.com
A109: IPS Privadas | B109: 110010101033 | D109: IPS CENTRO MEDICO DEPORTIVO BODYTECH GALERIAS | E109: WILSON FABIAN LEON RUIZ | F109: BogotᬠD.C. | G109: BogotᬠD.C | H109: carrera 24 No 53-73 piso 6 local 601 | I109: 7442222 EXT 48001 | J109: galerias@bodytechcorp.com
A110: IPS Privadas | B110: 110010101034 | D110: IPS CENTRO MEDICO DEPORTIVO BODYTECH PLAZA BOSA | E110: DARIO URUEс MACHADO | F110: BogotᬠD.C. | G110: BogotᬠD.C | H110: CALLE 65 SUR N 78H-51 LC 3-14 CC PLAZA BOSA | I110: 7442222 EXT 48400 | J110: plazabosa@bodytechcorp.com
A111: IPS Privadas | B111: 110010101035 | D111: IPS CENTRO MEDICO DEPORTIVO BODYTECH SANTA ANA | E111: CARLOS ANDRES BRICEя HUERTAS | F111: BogotᬠD.C. | G111: BogotᬠD.C | H111: CL 110 # 9A 10 70 LOC ANCLA 1-2 | I111: 2136076 / 6752270 / 3183060927 | J111: nordic@bodytechcorp.com
A112: IPS Privadas | B112: 110010101036 | D112: IPS CENTRO MEDICO DEPORTIVO BODYTECH COUNTRY | E112: DIEGO ALEJANDRO MELO DUARTE | F112: BogotᬠD.C. | G112: BogotᬠD.C | H112: Calle 138 # 10-42 | I112: 3183414098-3183414086 | J112: gerente.gymhouse@bodytechcorp.com
A113: IPS Privadas | B113: 110010101037 | D113: IPS CENTRO MEDICO DEPORTIVO BODYTECH ENSUEя | E113: MELISA GERALDINE CALVO ORTIZ | F113: BogotᬠD.C. | G113: BogotᬠD.C | H113: CARRERA 51 No 59C SUR -93 LOCAL 206 | I113: 3178871398-3213046169 | J113: ensueno@bodytechcorp.com
A114: IPS Privadas | B114: 110010101038 | D114: IPS CENTRO MEDICO DEPORTIVO BODYTECH CALLE 90 | E114: LYDY YANETH VILLANUEVA HERNANDEZ | F114: BogotᬠD.C. | G114: BogotᬠD.C | H114: CL 90 No 16-34 | I114: 7442222 EXT 3800 - 38004 | J114: calle90@bodytechcorp.com
A115: IPS Privadas | B115: 110010101039 | D115: IPS CENTRO MEDICO DEPORTIVO ATHLETIC HUB 72 | E115: ERIK DAVID MESA FERRUCHO | F115: BogotᬠD.C. | G115: BogotᬠD.C | H115: CR 24 # 71 A 85 | I115: 3008512774 - 7442222 | J115: hub72.gerente@athleticgym.com.co
A116: IPS Privadas | B116: 110010101040 | D116: IPS CENTRO MEDICO DEPORTIVO ATHLETIC RESTREPO | E116: CAMILO ANDRES DIAZ ESPITIA | F116: BogotᬠD.C. | G116: BogotᬠD.C | H116: CR 22 No 14-31 SUR | I116: 3163184277 | J116: restrepo.gerente@athleticgym.com.co
A117: IPS Privadas | B117: 110010101041 | D117: IPS CENTRO MEDICO DEPORTIVO BODYTECH PASEO DEL RIO | E117: SANDRA YANETH ARAOZ USECHE | F117: BogotᬠD.C. | G117: BogotᬠD.C | H117: Dg 57 C Sur # 62 - 60 Piso 4 Local 401 CC Paseo Villa Del Rio | I117: 3203119132 | J117: villadelrio@bodytechcorp.com
A118: IPS Privadas | B118: 110010101042 | D118: IPS CENTRO MEDICO DEPORTIVO BODYTECH CONNECTA | E118: WILSON FABIAN LEON RUIZ | F118: BogotᬠD.C. | G118: BogotᬠD.C | H118: Av Cl 26 # 92-32 MD 64 Y 65 PISO 4 | I118: 3148773075 | J118: conecta@bodytechcorp.com
...

Sheet SAO (aliado)
A1: SAO — migración a Fail Fast (ERP)
A3: Precios y supuestos
A4: $/usuario · Contabilidad | B4: 49
A5: $/usuario · Salud (HC) | B5: 79
A6: $/usuario · TMS | B6: 99
A7: Usuarios promedio / empresa | B7: 3
A8: Conversión a Fail Fast (semestre) | B8: 0.6
A10: Empresas (4) — completar nombre y tipo
A11: Empresa | B11: Tipo | C11: Usuarios | D11: $/usuario | E11: MRR
C12: 3 | D12: =IF(B12="Salud",$B$5,IF(B12="TMS",$B$6,IF(B12="","",$B$4))) | E12: =IF(B12="","",C12*D12)
C13: 3 | D13: =IF(B13="Salud",$B$5,IF(B13="TMS",$B$6,IF(B13="","",$B$4))) | E13: =IF(B13="","",C13*D13)
C14: 3 | D14: =IF(B14="Salud",$B$5,IF(B14="TMS",$B$6,IF(B14="","",$B$4))) | E14: =IF(B14="","",C14*D14)
C15: 3 | D15: =IF(B15="Salud",$B$5,IF(B15="TMS",$B$6,IF(B15="","",$B$4))) | E15: =IF(B15="","",C15*D15)
A16: Total | C16: =COUNTA(A12:A15) -> 0 | E16: =SUM(E12:E15) -> 0
A18: MRR semestre (potencial × conversión) | B18: =E16*B8 -> 0
A20: Plantilla: ingresa las 4 empresas de SAO (nombre + tipo). El MRR se calcula solo.

Sheet Plan de equipo
A1: Plan de equipo · capacidad para ejecutar
A3: Supuestos de capacidad
A4: Horas productivas / persona / mes | B4: 120
A5: % automatización IA en implementación | B5: 0
A6: Horas impl · IPS Nivel 1 | B6: 40
A7: Horas impl · Transporte TMS | B7: 40
A8: Horas impl · Grandes (agente CxP) | B8: 20
A9: Horas impl · Migración aliado (contab.) | B9: 12
A10: Cierres / mes por vendedor (AE) | B10: 7
A11: Equipo de producto (ingenieros, fijo) | B11: 3
A12: Costo cargado / persona / mes (USD) | B12: 2265
A13: Meses del plan | B13: =Supuestos!B5 -> 6
A15: Carga de implementación · Fail Fast directo
A16: Segmento | B16: Deploys | C16: Horas c/u | D16: Horas totales (con IA)
A17: IPS Nivel 1 | B17: =Supuestos!B35 -> 15 | C17: =$B$6 -> 40 | D17: =B17*C17*(1-$B$5) -> 600
A18: Transporte TMS | B18: =Supuestos!B29 -> 20 | C18: =$B$7 -> 40 | D18: =B18*C18*(1-$B$5) -> 800
A19: Grandes (agente) | B19: =Supuestos!B21 -> 40 | C19: =$B$8 -> 20 | D19: =B19*C19*(1-$B$5) -> 800
A20: Total horas implementación | D20: =SUM(D17:D19) -> 2200
A21: FTE implementación (horas ÷ meses ÷ productivas) | D21: =D20/B13/B4 -> 3.0555556
A23: Equipo Fail Fast (sin fundadores)
A24: Rol | B24: FTE | C24: Headcount
A25: Ventas / AE (IPS+Transp+Grandes) | B25: =(Supuestos!B35+Supuestos!B29+Supuestos!B21)/B13/B10 -> 1.7857143 | C25: =ROUNDUP(B25,0) -> 2
A26: SDR / sales engineer (talleres, demos) | B26: =ROUNDUP(((Supuestos!B29+Supuestos!B35)*17/40)/B13/4,1) -> 0.7 | C26: =ROUNDUP(B26,0) -> 1
A27: Implementación | B27: =D21 -> 3.0555556 | C27: =ROUNDUP(B27,0) -> 4
A28: Producto (ingeniería) | B28: =B11 -> 3 | C28: =ROUNDUP(B28,0) -> 3
A29: Total Fail Fast | B29: =SUM(B25:B28) -> 8.5412698 | C29: =SUM(C25:C28) -> 10
A31: Equipo aliado · Simba (fuera de nómina Fail Fast)
A32: Migraciones (Simba) | B32: ='Aliados — resumen'!E6 -> 95
A33: Horas totales (migración × horas × (1-IA)) | B33: =B32*B9*(1-B5) -> 1140
A34: FTE Simba para migración | B34: =B33/B13/B4 -> 1.5833333
A36: Costo y eficiencia de capital
A37: Costo mensual equipo FF | B37: =C29*B12 -> 22650
A38: MRR plan total (salida) | B38: ='Puente a 100K'!D9 -> 77885.8
A39: Costo equipo / MRR | B39: =B37/B38 -> 0.29081039
A40: ARR / persona FF | B40: =B38*12/C29 -> 93462.96
A42: Cómo leerlo
A43: • La PALANCA es el % de automatización IA (B5). Súbelo y caen los implementadores — es tu tesis de margen.
A44: • La migración de aliados la ejecuta Simba con su propio equipo: no suma a la nómina de Fail Fast.
A45: • Secuencia: 1º un closer/sales engineer (libera al fundador). Implementadores según demanda real. Producto nunca se starve.
A46: • A 0% de automatización el equipo es más pesado; con IA en implementación, baja a la mitad. Ese es el caso capital-eficiente.

Sheet Gráfico1 Top 10 Departamentos c
A3: Departamento | B3: Empresas
A4: ANTIOQUIA | B4: 514
A5: ATLANTICO | B5: 315
A6: BOLÍVAR | B6: 307
A7: BOYACA | B7: 306
A8: CESAR | B8: 113
A9: CUNDINAMARCA | B9: 1255
A10: META | B10: 274
A11: NORTE DE SANTAN | B11: 123
A12: SANTANDER | B12: 211
A13: VALLE DEL CAUCA | B13: 261

Sheet Gráfico1 Contribución al Plan d
A3: Segmento | B3: MRR
A4: Expansión (NRR) | B4: 5000
A5: Grandes — agente CxP (land) | B5: 16000
A6: IPS Nivel 1 | B6: 22500
A7: Migración aliados (Simba+SAO) | B7: 14545.8
A8: Transporte TMS | B8: 19840
